Workbook

Sheet Dashboard
A1: Tata Power — Double Materiality Assessment
A2: Executive ESG Dashboard | Impact & Financial Materiality | FY2025–26
A4: ESG TOPICS ASSESSED | D4: DOUBLE MATERIAL | G4: IMPACT MATERIAL | J4: FINANCIALLY MATERIAL | M4: BELOW THRESHOLD
A5: =COUNTA('DMA Matrix'!A5:A34) -> 30 | D5: =COUNTIF('DMA Matrix'!H5:H34,"Double Material") -> 22 | G5: =COUNTIF('DMA Matrix'!H5:H34,"Impact Material") -> 7 | J5: =COUNTIF('DMA Matrix'!H5:H34,"Financially Material") -> 1 | M5: =COUNTIF('DMA Matrix'!H5:H34,"Below Threshold") -> 0
J9: Materiality by ESG Category
J10: Environmental | K10: =COUNTIFS('DMA Matrix'!B5:B34,"Environmental",'DMA Matrix'!H5:H34,"Double Material") -> 6
J11: Social | K11: =COUNTIFS('DMA Matrix'!B5:B34,"Social",'DMA Matrix'!H5:H34,"Double Material") -> 7
J12: Governance | K12: =COUNTIFS('DMA Matrix'!B5:B34,"Governance",'DMA Matrix'!H5:H34,"Double Material") -> 9
A27: Key Takeaways | J27: Key Strategic ESG Themes
A28: ="01 | Broad ESG Materiality — "&IF(M5=0,"All "&A5&" assessed ESG topics",(A5-M5)&" of "&A5&" assessed ESG topics")&" cross at least one materiality threshold." -> 01 | Broad ESG Materiality — All 30 assessed ESG topics cross at least one materiality threshold. | J28: 01 | Climate & Decarbonisation -Climate Change • GHG Emissions • Energy Management • Clean Technology
A29: ="02 | Strong Double Materiality — "&D5&" of "&A5&" topics ("&TEXT(D5/A5,"0.0%")&") are material from both impact and financial perspectives." -> 02 | Strong Double Materiality — 22 of 30 topics (73.3%) are material from both impact and financial perspectives. | J29: 02 | Environmental & Resource Stewardship -Air Pollution • Water • Waste • Ash • Biodiversity • Resource Efficiency
A30: ="03 | Governance Concentration — "&K12&" of "&COUNTIF('DMA Matrix'!B5:B34,"Governance")&" governance topics are classified as Double Material." -> 03 | Governance Concentration — 9 of 10 governance topics are classified as Double Material. | J30: 03 | Safe, Reliable & Affordable Energy- OHS • Energy Reliability • Access & Affordability • Customer Protection
A31: ="04 | Benchmarked — Alignment Index "&TEXT(Benchmark!C21,"0%")&" and top-band recall "&TEXT(Benchmark!C22,"0%")&" against Tata Power's official FY26 DMA (Grade "&Benchmark!C24&")." -> 04 | Benchmarked — Alignment Index 85% and top-band recall 60% against Tata Power's official FY26 DMA (Grade B: Moderate). | J31: 04 | People, Communities & Responsible Value Chain - Human Rights • Labour Practices • Community Impact • D&I • Supply Chain
J32: 05 | Governance, Digital & ESG Risk Resilience - Regulatory Compliance • ESG Governance • ESG Risk • Cybersecurity • Data Privacy
A33: Assessment Scope
A34: Sr. No | B34: Parameter | E34: Details
A35: 1 | B35: Company | E35: Tata Power Company Limited
A36: 2 | B36: Assessment Period | E36: FY2025–26
A37: 3 | B37: ESG Topics | E37: =A5 -> 30
A38: 4 | B38: Assessment Dimensions | E38: Impact + Financial Materiality
A39: 5 | B39: Evidence Base | E39: Publicly available information
A40: 6 | B40: Assessment Type | E40: Independent analytical assessment
A41: 7 | B41: Benchmark & sync | E41: ="Alignment "&TEXT(Benchmark!C21,"0%")&" | Grade "&LEFT(Benchmark!C24,1)&" | Workbook sync: " -> Alignment 85% | Grade B | Workbook sync:
A42: Disclaimer: This is an independent analytical assessment based on publicly available information and does not represent Tata Power's official DMA.

Sheet Company Context
A1: Tata Power — Integrated Energy Platform Navigating India's Energy Transition
A2: Business scale, clean-energy expansion and increasing ESG complexity shape the materiality landscape
A4: Tata Power at a Glance | FY2025 - 26
A5: 16,716 MW | B5: 7,856 MW | C5: 13.1+ Mn | G5: ₹63,681 Cr | J5: ₹16,090 Cr
A6: Generation Portfolio | B6: Clean & Green Operational Capacity | C6: Distribution Customers | G6: Revenue | J6: EBITDA
A9: Clean & green capacity represented ~47% of Tata Power’s operational portfolio in FY26.
A12: Why Materiality Matters for Tata Power | D12: Integrated Energy Value Chain
D13: GENERATION → TRANSMISSION → DISTRIBUTION → RENEWABLES → ENERGY SOLUTIONS
A14: 01 | Energy Transition
A15: Decarbonisation • GHG emissions • Energy efficiency • Clean technology | D15: Generation | F15: Thermal • Hydro • Solar • Wind • Waste Heat Recovery
A16: 02 | Environmental Footprint | D16: Transmission | F16: 7,403 ckm transmission portfolio
A17: Water • Air pollution • Ash • Waste • Biodiversity • Land use | D17: Distribution | F17: 13.1+ million customers across India
A18: 03 | Stakeholder Dependence | D18: Renewables | F18: Solar • Wind • Hydro • Rooftop Solar • Storage
A19: Employees • Contractors • Customers • Communities • Suppliers | D19: Energy Solutions | F19: EV Charging • Rooftop Solar • Microgrids • Digital Energy Solutions
A20: 04 | Infrastructure & Digital Resilience
A21: Energy reliability • Cybersecurity • Data privacy • Supply-chain resilience | D21: Tata Power operates across the power value chain, combining conventional generation with expanding clean-energy and customer-facing businesses
A25: Strategic Context
A26: Tata Power’s integrated business model creates a dual ESG challenge: scaling clean, reliable and affordable energy while managing the environmental, social and governance impacts of a large infrastructure-intensive power business.
A29: DMA Implication:
A30: The assessment therefore considers both Tata Power’s impacts on people and the environment and the financial implications of ESG-related risks and opportunities.
A32: Source: Tata Power Integrated Annual Report FY2025–26 and corporate disclosures. FY2025–26 figures unless otherwise stated
A33: Independent analytical assessment based on publicly available information; not Tata Power’s official DMA.

Sheet ESG Issue Universe
A1: Tata Power - ESG Issue Universe
A3: Issue Id | B3: ESG Category | C3: ESG Topic | D3: Sub Topic | E3: Why Relevant to Tata Power | F3: Value Chain Stage
A4: E01 | B4: Environmental | C4: Climate Change | D4: Climate transition | E4: Tata Power is transitioning its portfolio toward clean energy while managing the long-term transition of conventional generation. | F4: Generation | Renewables | Transmission & Distribution
A5: E02 | B5: Environmental | C5: GHG Emissions | D5: Scope 1, 2 & 3 | E5: Power generation is emissions-intensive; Tata Power therefore needs to reduce operational emissions and manage value-chain emissions. | F5: Generation | Supply Chain | T&D
A6: E03 | B6: Environmental | C6: Energy Management | D6: Energy efficiency | E6: Energy efficiency across generation, transmission and distribution can reduce resource consumption, losses and operating costs. | F6: Generation | T&D | Energy Solutions
A7: E04 | B7: Environmental | C7: Air Pollution | D7: SOx, NOx, PM | E7: Thermal generation can create air-emission impacts, making emission-control systems and regulatory compliance important. | F7: Thermal Generation | Supply Chain
A8: E05 | B8: Environmental | C8: Water | D8: Water withdrawal & consumption | E8: Power generation requires significant water resources, making water efficiency and conservation important for operational resilience. | F8: Thermal & Hydro Generation | Communities
A9: E06 | B9: Environmental | C9: Biodiversity | D9: Ecosystem impact | E9: Large-scale generation, transmission and renewable projects can interact with ecosystems and biodiversity-sensitive areas. | F9: Generation | Transmission | Renewables
A10: E07 | B10: Environmental | C10: Waste Management | D10: Waste & recycling | E10: Diverse operations generate hazardous, non-hazardous and industrial waste requiring responsible treatment and disposal. | F10: Generation | Manufacturing | Projects
A11: E08 | B11: Environmental | C11: Ash Management | D11: Fly ash / bottom ash | E11: Thermal operations generate substantial ash, requiring utilisation, safe handling, storage and regulatory compliance. | F11: Thermal Generation | Supply Chain
A12: E09 | B12: Environmental | C12: Land Use | D12: Land footprint | E12: Utility-scale generation, transmission and renewable projects require significant land and can affect local ecosystems and communities. | F12: Generation | Transmission | Renewables
A13: E10 | B13: Environmental | C13: Resource Use & Circular Economy | D13: Materials & circularity | E13: Large infrastructure projects require metals, equipment and other resources, creating opportunities for resource efficiency and circularity. | F13: Projects | Manufacturing | Generation
A14: S01 | B14: Social | C14: Occupational Health & Safety | D14: Workplace safety | E14: Power generation, construction, transmission and distribution involve high-risk activities requiring strong safety management. | F14: Generation | Transmission | Distribution | Projects
... A33: G10 | B33: Governance | C33: Creating Economic Value | D33: Sustainable growth | E33: Tata Power must balance investment in energy transition and infrastructure with profitability, financial resilience and long-term value creation. | F33: All Operations | Corporate

Sheet Evidence Database
A1: Tata Power — ESG Evidence Database
A2: Publicly Disclosed Evidence Supporting Materiality Assessment | FY2025–26
A4: Issue Id | B4: ESG Topic | C4: Evidence /Observation | D4: Impact Relevance | E4: Financial Relevance | F4: Risk/ Opportunity | G4: Tata Power Response | H4: Source Document | I4: Page | J4: Source Type | K4: Evidence Strength | L4: Official FY26 topic & band
A5: E01 | B5: Climate Change | C5: Tata Power identifies continued exposure to thermal assets as a source of carbon-pricing and stranded-asset risk. The company also identifies renewable-energy expansion as an opportunity and targets Net Zero emissions by 2045. | D5: Thermal generation contributes to GHG emissions and climate impacts; transition toward renewable energy can reduce lifecycle emissions. | E5: Carbon pricing, transition costs, stranded assets and changing energy-market expectations can affect long-term competitiveness and capital allocation. | F5: Risk + Opportunity | G5: Project Aalingana, SBTi-aligned targets, renewable expansion and transition toward cleaner energy; Net Zero target before 2045. | H5: TATA POWER FY 2025-26 BRSR | I5: 293 | J5: Company Disclosure | K5: High | L5: =IFERROR(IF(INDEX(Benchmark!$K$33:$K$62,MATCH($A5,Benchmark!$A$33:$A$62,0))="n/a","No official equivalent",INDEX(Benchmark!$J$33:$J$62,MATCH($A5,Benchmark!$A$33:$A$62,0))&" - "&INDEX(Benchmark!$K$33:$K$62,MATCH($A5,Benchmark!$A$33:$A$62,0))),"") -> Climate strategy - Very High
A6: E02 | B6: GHG Emissions | C6: Tata Power reports Scope 1 and Scope 2 emissions and identifies high Scope 1 emissions from coal-based generation as a key risk. | D6: GHG emissions contribute to climate change and represent an environmental impact of thermal generation. | E6: Higher emissions can increase compliance, monitoring, retrofit and potential carbon-related costs. | F6: Risk + Opportunity | G6: Transition to lower-emission generation, renewable expansion, emissions reduction targets and pollution-control technologies. | H6: TATA POWER FY 2025-26 BRSR | I6: 293 | J6: Company Disclosure | K6: High | L6: =IFERROR(IF(INDEX(Benchmark!$K$33:$K$62,MATCH($A6,Benchmark!$A$33:$A$62,0))="n/a","No official equivalent",INDEX(Benchmark!$J$33:$J$62,MATCH($A6,Benchmark!$A$33:$A$62,0))&" - "&INDEX(Benchmark!$K$33:$K$62,MATCH($A6,Benchmark!$A$33:$A$62,0))),"") -> Emissions management - Very High
A7: E03 | B7: Energy Management | C7: Tata Power identifies high auxiliary power consumption and distribution losses as operational efficiency issues and identifies smart-grid technologies and energy-efficiency measures as opportunities. | D7: Inefficient energy use increases resource consumption and reduces energy efficiency. | E7: Higher energy losses and auxiliary consumption can increase operating costs and reduce efficiency. | F7: Risk + Opportunity | G7: Energy-efficiency measures, operational benchmarking, smart meters, grid digitalization and ISO 50001. | H7: TATA POWER FY 2025-26 BRSR | I7: 293 | J7: Company Disclosure | K7: High | L7: =IFERROR(IF(INDEX(Benchmark!$K$33:$K$62,MATCH($A7,Benchmark!$A$33:$A$62,0))="n/a","No official equivalent",INDEX(Benchmark!$J$33:$J$62,MATCH($A7,Benchmark!$A$33:$A$62,0))&" - "&INDEX(Benchmark!$K$33:$K$62,MATCH($A7,Benchmark!$A$33:$A$62,0))),"") -> Energy management - Very High
A8: E04 | B8: Air Pollution | C8: Tata Power identifies SOx, NOx and particulate/fugitive emissions from coal-based operations as environmental and health concerns. | D8: Air pollutants can affect local air quality, ecosystems and community health. | E8: Tightening emission standards can increase compliance, monitoring and retrofit costs. | F8: Risk + Opportunity | G8: Air Pollution Control Devices, fugitive-emission management, continuous monitoring and FGD/emission-control technologies. | H8: TATA POWER FY 2025-26 BRSR | I8: 293 | J8: Company Disclosure | K8: High | L8: =IFERROR(IF(INDEX(Benchmark!$K$33:$K$62,MATCH($A8,Benchmark!$A$33:$A$62,0))="n/a","No official equivalent",INDEX(Benchmark!$J$33:$J$62,MATCH($A8,Benchmark!$A$33:$A$62,0))&" - "&INDEX(Benchmark!$K$33:$K$62,MATCH($A8,Benchmark!$A$33:$A$62,0))),"") -> Emissions management - Very High
A9: E05 | B9: Water & Effluent | C9: Tata Power's operations depend on water, particularly thermal generation. FY26 water consumption was approximately 266.3 million KL, and the company identifies water stress and discharge requirements as operational and regulatory risks. | D9: Water withdrawal and heated effluent discharge can affect aquatic ecosystems, water quality and availability for surrounding communities. | E9: Water scarcity and tighter discharge regulations can create operational constraints, compliance costs and business interruption risk. | F9: Risk + Opportunity | G9: Water-efficiency measures, wastewater recycling, Zero Liquid Discharge, desalination, rainwater harvesting and 2030 water-neutrality goal. | H9: TATA POWER FY 2025-26 BRSR | I9: 294 | J9: Company Disclosure | K9: High | L9: =IFERROR(IF(INDEX(Benchmark!$K$33:$K$62,MATCH($A9,Benchmark!$A$33:$A$62,0))="n/a","No official equivalent",INDEX(Benchmark!$J$33:$J$62,MATCH($A9,Benchmark!$A$33:$A$62,0))&" - "&INDEX(Benchmark!$K$33:$K$62,MATCH($A9,Benchmark!$A$33:$A$62,0))),"") -> Water and effluent management - Very High
A10: E06 | B10: Biodiversity | C10: Tata Power's generation and infrastructure projects can interact with ecosystems and biodiversity. The company incorporates biodiversity conservation, afforestation, catchment treatment and environmental monitoring into relevant projects. | D10: Power infrastructure can affect habitats, ecosystems and biodiversity. | E10: Biodiversity impacts can create regulatory, approval, project-delay and stakeholder risks. | F10: Risk + Opportunity | G10: Biodiversity conservation, environmental assessments, afforestation, catchment treatment and monitoring. | H10: TATA POWER FY 2025-26 BRSR | I10: 324- 325 | J10: Company Disclosure | K10: High | L10: =IFERROR(IF(INDEX(Benchmark!$K$33:$K$62,MATCH($A10,Benchmark!$A$33:$A$62,0))="n/a","No official equivalent",INDEX(Benchmark!$J$33:$J$62,MATCH($A10,Benchmark!$A$33:$A$62,0))&" - "&INDEX(Benchmark!$K$33:$K$62,MATCH($A10,Benchmark!$A$33:$A$62,0))),"") -> Safeguarding biodiversity - High
A11: E07 | B11: Waste Management | C11: Tata Power identifies major waste streams including fly ash from thermal power plants and chemical sludge from solar PV manufacturing. It also discusses recycling pathways for end-of-life solar panels | D11: Improper waste management can cause pollution and environmental impacts. | E11: Waste-treatment, disposal and compliance requirements create operating costs; circularity can create resource-efficiency opportunities | F11: Risk + Opportunity | G11: Fly-ash utilization, bottom-ash utilization and development of recycling pathways for end-of-life PV panels. | H11: TATA POWER FY 2025-26 BRSR | I11: 323 | J11: Company Disclosure | K11: High | L11: =IFERROR(IF(INDEX(Benchmark!$K$33:$K$62,MATCH($A11,Benchmark!$A$33:$A$62,0))="n/a","No official equivalent",INDEX(Benchmark!$J$33:$J$62,MATCH($A11,Benchmark!$A$33:$A$62,0))&" - "&INDEX(Benchmark!$K$33:$K$62,MATCH($A11,Benchmark!$A$33:$A$62,0))),"") -> Hazardous and toxic waste management - High
A12: E08 | B12: Ash Management | C12: Tata Power identifies fly ash as a major waste stream from thermal power plants and reports its utilization in construction, ready-mix concrete, cement and quarry filling. | D12: Poor ash management can create risks of land, air and water contamination. | E12: Ash handling, disposal and compliance require expenditure, while utilization creates potential cost/resource-efficiency benefits. | F12: Risk + Opportunity | G12: Fly-ash utilization through authorized vendors and increased bottom-ash utilization. | H12: TATA POWER FY 2025-26 BRSR | I12: 323 | J12: Company Disclosure | K12: High | L12: =IFERROR(IF(INDEX(Benchmark!$K$33:$K$62,MATCH($A12,Benchmark!$A$33:$A$62,0))="n/a","No official equivalent",INDEX(Benchmark!$J$33:$J$62,MATCH($A12,Benchmark!$A$33:$A$62,0))&" - "&INDEX(Benchmark!$K$33:$K$62,MATCH($A12,Benchmark!$A$33:$A$62,0))),"") -> No official equivalent
A13: E09 | B13: Land Use | C13: Tata Power identifies the large land footprint associated with solar/wind farms as potentially affecting land use and local ecosystems. | D13: Large energy infrastructure projects can alter land use and affect local ecosystems and communities. | E13: Land availability, approvals, project development and stakeholder issues can affect project timelines and costs. | F13: Risk + Opportunity | G13: Environmental approvals, biodiversity conservation, catchment protection and environmental management measures. | H13: TATA POWER FY 2025-26 BRSR | I13: 294 | J13: Company Disclosure | K13: Medium - High | L13: =IFERROR(IF(INDEX(Benchmark!$K$33:$K$62,MATCH($A13,Benchmark!$A$33:$A$62,0))="n/a","No official equivalent",INDEX(Benchmark!$J$33:$J$62,MATCH($A13,Benchmark!$A$33:$A$62,0))&" - "&INDEX(Benchmark!$K$33:$K$62,MATCH($A13,Benchmark!$A$33:$A$62,0))),"") -> No official equivalent
A14: E10 | B14: Resource Use & Circular Economy. | C14: Tata Power describes resource-efficiency measures and circularity initiatives, including PV-panel end-of-life management, recycling pathways and waste utilization | D14: Efficient resource use reduces waste and pressure on natural resources. | E14: Better resource efficiency can reduce material/waste costs and create opportunities for recovery and recycling. | F14: Risk + Opportunity | G14: Waste utilization, PV recycling pathways and circular-economy initiatives. | H14: TATA POWER FY 2025-26 BRSR | I14: 323 | J14: Company Disclosure | K14: Medium - High | L14: =IFERROR(IF(INDEX(Benchmark!$K$33:$K$62,MATCH($A14,Benchmark!$A$33:$A$62,0))="n/a","No official equivalent",INDEX(Benchmark!$J$33:$J$62,MATCH($A14,Benchmark!$A$33:$A$62,0))&" - "&INDEX(Benchmark!$K$33:$K$62,MATCH($A14,Benchmark!$A$33:$A$62,0))),"") -> Product design and lifecycle management* - Medium
L15: =IFERROR(IF(INDEX(Benchmark!$K$33:$K$62,MATCH($A15,Benchmark!$A$33:$A$62,0))="n/a","No official equivalent",INDEX(Benchmark!$J$33:$J$62,MATCH($A15,Benchmark!$A$33:$A$62,0))&" - "&INDEX(Benchmark!$K$33:$K$62,MATCH($A15,Benchmark!$A$33:$A$62,0))),"")
A16: S01 | B16: Occupational Health & Safety | C16: Tata Power identifies occupational health and safety as a material issue. In FY26, it maintained an Occupational Health & Safety Management System aligned with Tata Group standards and ISO 45001:2018, trained 100% of employees and business-associate workforce on OH&S systems, and conducted 757 safety capability workshops involving 18,920 personnel. | D16: Power generation, transmission and distribution involve significant physical and operational hazards. Workplace incidents can cause injury, health impacts and potentially fatalities. | E16: Safety incidents can lead to medical and compensation costs, litigation, operational disruption, workforce availability issues and reputational damage. | F16: Risk + Opportunity | G16: ISO 45001-aligned OH&S management system, HIRA/JSA, safety training, PPE, audits, automation/mechanisation and business-associate safety programmes. | H16: Tata Power FY2025–26 Integrated Annual Report | I16: 294 -95 | J16: Company Disclosure | K16: High | L16: =IFERROR(IF(INDEX(Benchmark!$K$33:$K$62,MATCH($A16,Benchmark!$A$33:$A$62,0))="n/a","No official equivalent",INDEX(Benchmark!$J$33:$J$62,MATCH($A16,Benchmark!$A$33:$A$62,0))&" - "&INDEX(Benchmark!$K$33:$K$62,MATCH($A16,Benchmark!$A$33:$A$62,0))),"") -> Occupational health and safety - Very High
A17: S02 | B17: Employee Wellbeing | C17: Tata Power describes employee wellbeing, engagement and a safe, inclusive workplace as priorities. FY26 initiatives included mental wellbeing, stress management, financial health, nutrition, preventive healthcare, employee surveys and leadership interactions. | D17: Employee wellbeing affects physical, mental and social health and the quality of the working environment. | E17: Poor employee wellbeing can contribute to absenteeism, lower productivity, turnover and higher workforce costs. | F17: Risk + Opportunity | G17: "A Fuller Life" framework, employee assistance programmes, health screening, counselling, wellbeing initiatives and engagement programmes. | H17: Tata Power FY2025–26 Integrated Annual Report | I17: 125 - 135 | J17: Company Disclosure | K17: High | L17: =IFERROR(IF(INDEX(Benchmark!$K$33:$K$62,MATCH($A17,Benchmark!$A$33:$A$62,0))="n/a","No official equivalent",INDEX(Benchmark!$J$33:$J$62,MATCH($A17,Benchmark!$A$33:$A$62,0))&" - "&INDEX(Benchmark!$K$33:$K$62,MATCH($A17,Benchmark!$A$33:$A$62,0))),"") -> Responsible employer - Medium
A18: S03 | B18: Diversity & Inclusion | C18: Tata Power identifies diversity and inclusion as a material social topic and states that it aims to create an inclusive workplace across levels. FY26 initiatives included women leadership development and targeted inclusion programmes. | D18: Workplace diversity and inclusion affect equality of opportunity, employee experience and representation. | E18: Effective diversity and inclusion can influence talent attraction, retention, engagement and leadership pipeline development. | F18: Risk + Opportunity | G18: Diversity and inclusion programmes, women leadership development, targeted workforce initiatives and inclusive workplace policies. | H18: Tata Power FY2025–26 Integrated Annual Report | I18: 125 - 135 | J18: Company Disclosure | K18: High | L18: =IFERROR(IF(INDEX(Benchmark!$K$33:$K$62,MATCH($A18,Benchmark!$A$33:$A$62,0))="n/a","No official equivalent",INDEX(Benchmark!$J$33:$J$62,MATCH($A18,Benchmark!$A$33:$A$62,0))&" - "&INDEX(Benchmark!$K$33:$K$62,MATCH($A18,Benchmark!$A$33:$A$62,0))),"") -> Diversity and inclusion in workplace - Medium
A19: S04 | B19: Talent Development | C19: Tata Power identifies employee retention, engagement and talent development as material and reports structured learning, leadership development, technical training and internal mobility programmes. | D19: Training and development improve employee capability, employability and career progression. | E19: Skill development supports productivity, operational capability, retention and the ability to execute the energy transition. | F19: Risk + Opportunity | G19: Structured learning, leadership programmes, technical training, WILP and internal mobility. | H19: Tata Power FY2025–26 Integrated Annual Report | I19: 125 - 135 | J19: Company Disclosure | K19: High | L19: =IFERROR(IF(INDEX(Benchmark!$K$33:$K$62,MATCH($A19,Benchmark!$A$33:$A$62,0))="n/a","No official equivalent",INDEX(Benchmark!$J$33:$J$62,MATCH($A19,Benchmark!$A$33:$A$62,0))&" - "&INDEX(Benchmark!$K$33:$K$62,MATCH($A19,Benchmark!$A$33:$A$62,0))),"") -> Employee retention, engagement and talent development - High
A20: S05 | B20: Labour Practices | C20: Tata Power identifies labour management as a material topic and recognizes potential operational disruption from labour issues. It states that labour compliance is maintained according to regulatory requirements and global standards such as ILO principles. | D20: Poor labour practices can affect employee rights, working conditions and industrial relations. | E20: Labour disputes or workforce disruption can cause downtime, productivity losses and additional operating costs. | F20: Risk | G20: Labour compliance, alignment with regulatory requirements and international labour standards. | H20: Tata Power FY2025–26 BRSR | I20: 294 - 295 | J20: Company Disclosure | K20: High | L20: =IFERROR(IF(INDEX(Benchmark!$K$33:$K$62,MATCH($A20,Benchmark!$A$33:$A$62,0))="n/a","No official equivalent",INDEX(Benchmark!$J$33:$J$62,MATCH($A20,Benchmark!$A$33:$A$62,0))&" - "&INDEX(Benchmark!$K$33:$K$62,MATCH($A20,Benchmark!$A$33:$A$62,0))),"") -> Labour management - High
A21: S06 | B21: Human Rights | C21: Tata Power's Human Rights Commitment Framework covers dignity, freedom of association, collective bargaining, non-discrimination, prohibition of child and forced labour, and alignment with ILO and UN Global Compact principles. | D21: Power-sector operations and supply chains can affect workers, communities and other stakeholders, making human-rights protection important. | E21: Human-rights violations can create legal, operational, reputational and stakeholder risks. | F21: Risk | G21: Human Rights Commitment Framework, human-rights assessments, training and alignment with international labour standards. | H21: Tata Power FY2025–26 Integrated Annual Report | I21: ~125–135 / 298–299 | J21: Company Disclosure | K21: High | L21: =IFERROR(IF(INDEX(Benchmark!$K$33:$K$62,MATCH($A21,Benchmark!$A$33:$A$62,0))="n/a","No official equivalent",INDEX(Benchmark!$J$33:$J$62,MATCH($A21,Benchmark!$A$33:$A$62,0))&" - "&INDEX(Benchmark!$K$33:$K$62,MATCH($A21,Benchmark!$A$33:$A$62,0))),"") -> Human rights - High
A22: S07 | B22: Community Impact | C22: Tata Power states that its community initiatives focus on inclusive growth and resilience, particularly in underserved communities. Its CSR approach covers areas including education, employability, entrepreneurship and essential enablers. (FY26 CSR expenditure was reported at approximately ₹100.54 crore) | D22: Large energy projects can affect communities through employment, infrastructure, land use, environmental impacts and access to energy. | E22: Weak community relationships can create stakeholder opposition, delays, reputational issues and project-development risks. | F22: Risk + Opportunity | G22: CSR programmes, community engagement and initiatives focused on education, employment, entrepreneurship and essential enablers. | H22: Tata Power FY2025–26 Integrated Annual Report | I22: 292 / 146–167 | J22: Company disclosure | K22: High | L22: =IFERROR(IF(INDEX(Benchmark!$K$33:$K$62,MATCH($A22,Benchmark!$A$33:$A$62,0))="n/a","No official equivalent",INDEX(Benchmark!$J$33:$J$62,MATCH($A22,Benchmark!$A$33:$A$62,0))&" - "&INDEX(Benchmark!$K$33:$K$62,MATCH($A22,Benchmark!$A$33:$A$62,0))),"") -> Building sustainable communities - High
A23: S08 | B23: Access & Affordability | C23: Tata Power identifies access and affordability as a newly added material topic, reflecting the importance of inclusive access to reliable and affordable electricity. (The company reports a distribution customer base of 13.1+ million and emphasizes reliable and affordable energy access) | D23: Electricity access and affordability directly affect household welfare, economic opportunity and quality of life. | E23: Affordability and access influence demand, customer retention, collections and the long-term sustainability of distribution businesses. | F23: Risk + Opportunity | G23: Distribution network expansion, digitalisation, smart metering, customer-centric services, rooftop solar and clean-energy solutions. | H23: Tata Power FY2025–26 Integrated Annual Report / Materiality Assessment | I23: 80 - 90 | J23: Company disclosure | K23: High | L23: =IFERROR(IF(INDEX(Benchmark!$K$33:$K$62,MATCH($A23,Benchmark!$A$33:$A$62,0))="n/a","No official equivalent",INDEX(Benchmark!$J$33:$J$62,MATCH($A23,Benchmark!$A$33:$A$62,0))&" - "&INDEX(Benchmark!$K$33:$K$62,MATCH($A23,Benchmark!$A$33:$A$62,0))),"") -> Access and affordability* - High
A24: S09 | B24: Customer Welfare | C24: Tata Power identifies customer relationship management as a material topic. The company states that poor service quality could lead to customer loss and uses multiple customer-feedback channels. Its FY26 C.A.R.E. initiative covered 10,343 employees across 22 locations in the Odisha DISCOMs to strengthen customer-centric service delivery. | D24: Electricity customers depend on reliable, responsive and fair service. | E24: Poor customer experience can result in customer dissatisfaction, complaints, collection issues, reputational damage and revenue impacts. | F24: Risk + Opportunity | G24: Customer-feedback mechanisms, C.A.R.E. initiative, digital platforms and customer-centric service programmes. | H24: Tata Power FY2025–26 Integrated Annual Report | I24: 110 - 119 | J24: Company disclosure | K24: High | L24: =IFERROR(IF(INDEX(Benchmark!$K$33:$K$62,MATCH($A24,Benchmark!$A$33:$A$62,0))="n/a","No official equivalent",INDEX(Benchmark!$J$33:$J$62,MATCH($A24,Benchmark!$A$33:$A$62,0))&" - "&INDEX(Benchmark!$K$33:$K$62,MATCH($A24,Benchmark!$A$33:$A$62,0))),"") -> Customer relationship management - High
A25: S10 | B25: Energy Reliability | C25: Tata Power operates generation, transmission and distribution businesses and emphasizes reliable energy supply, resilient distribution networks and grid infrastructure. Its FY26 strategy includes strengthening distribution businesses and developing resilient energy infrastructure. | D25: Electricity reliability affects households, businesses, public services and economic activity. | E25: Power interruptions can cause service penalties, customer dissatisfaction, operational losses and reputational damage. | F25: Risk + Opportunity | G25: Grid modernization, smart meters, digitalisation, transmission expansion and distribution network improvements. | H25: Tata Power FY2025–26 Integrated Annual Report | I25: 294 | J25: Company disclosure | K25: High | L25: =IFERROR(IF(INDEX(Benchmark!$K$33:$K$62,MATCH($A25,Benchmark!$A$33:$A$62,0))="n/a","No official equivalent",INDEX(Benchmark!$J$33:$J$62,MATCH($A25,Benchmark!$A$33:$A$62,0))&" - "&INDEX(Benchmark!$K$33:$K$62,MATCH($A25,Benchmark!$A$33:$A$62,0))),"") -> Continuous and affordable green power - Very High
L26: =IFERROR(IF(INDEX(Benchmark!$K$33:$K$62,MATCH($A26,Benchmark!$A$33:$A$62,0))="n/a","No official equivalent",INDEX(Benchmark!$J$33:$J$62,MATCH($A26,Benchmark!$A$33:$A$62,0))&" - "&INDEX(Benchmark!$K$33:$K$62,MATCH($A26,Benchmark!$A$33:$A$62,0))),"")
A27: G01 | B27: Business Ethics — Anti-corruption | C27: Tata Power identifies Ethical Business Conduct as a material governance topic. The Tata Code of Conduct (TCoC) provides the framework for ethical behaviour, while employees, customers and suppliers are expected to adhere to relevant principles. | D27: Ethical misconduct, bribery or corruption can negatively affect employees, business partners, customers and institutional trust. | E27: Ethical violations can result in penalties, litigation, loss of business relationships and reputational damage. | F27: Risk | G27: TCoC, anti-bribery and anti-corruption training, whistleblower mechanism, ethics investigations and annual compliance processes. | H27: FY26 Integrated Annual Report / Tata Power Ethics | I27: 82; Ethics section | J27: Tata Power Annual Report / Corporate website | K27: High | L27: =IFERROR(IF(INDEX(Benchmark!$K$33:$K$62,MATCH($A27,Benchmark!$A$33:$A$62,0))="n/a","No official equivalent",INDEX(Benchmark!$J$33:$J$62,MATCH($A27,Benchmark!$A$33:$A$62,0))&" - "&INDEX(Benchmark!$K$33:$K$62,MATCH($A27,Benchmark!$A$33:$A$62,0))),"") -> Ethical business conduct - Very High
A28: G02 | B28: Regulatory Compliance — Legal & Regulatory | C28: Tata Power identifies Regulatory Compliance and Landscape as a material topic. The power sector is highly regulated across generation, transmission, distribution, environment, safety and consumer matters. | D28: Non-compliance can affect customers, employees, communities and the environment. | E28: Regulatory changes or non-compliance can lead to penalties, operational disruption, additional compliance costs and project delays. | F28: Risk | G28: Regulatory monitoring, policy advocacy, compliance mechanisms and engagement with regulators and policymakers. | H28: FY26 Integrated Annual Report | I28: 82–83 | J28: Tata Power Annual Report | K28: High | L28: =IFERROR(IF(INDEX(Benchmark!$K$33:$K$62,MATCH($A28,Benchmark!$A$33:$A$62,0))="n/a","No official equivalent",INDEX(Benchmark!$J$33:$J$62,MATCH($A28,Benchmark!$A$33:$A$62,0))&" - "&INDEX(Benchmark!$K$33:$K$62,MATCH($A28,Benchmark!$A$33:$A$62,0))),"") -> Regulatory compliance and landscape - High
A29: G03 | B29: ESG Governance — Board Oversight | C29: Tata Power identifies ESG Governance as a very high-priority material issue. Its governance structure integrates sustainability considerations into strategic decision-making and oversight. | D29: Strong ESG governance influences how environmental and social impacts are identified, managed and monitored. | E29: Weak ESG integration can affect investor confidence, access to capital, compliance and strategic decision-making. | F29: Risk + Opportunity | G29: CSR & Sustainability Board Committee, ESG governance structure, leadership review and integration of ESG into business strategy. | H29: FY26 BRSR / Integrated Annual Report | I29: 295; 82 | J29: Tata Power BRSR / Annual Report | K29: High | L29: =IFERROR(IF(INDEX(Benchmark!$K$33:$K$62,MATCH($A29,Benchmark!$A$33:$A$62,0))="n/a","No official equivalent",INDEX(Benchmark!$J$33:$J$62,MATCH($A29,Benchmark!$A$33:$A$62,0))&" - "&INDEX(Benchmark!$K$33:$K$62,MATCH($A29,Benchmark!$A$33:$A$62,0))),"") -> ESG governance - Very High
A30: G04 | B30: Risk Management — ESG Risk | C30: Tata Power identifies Risk Management and BCDMP (Business Continuity & Disaster Management Plan) as a material topic. Its operations face physical, operational, climate, cyber, regulatory and business-continuity risks. | D30: Effective risk management reduces potential impacts on employees, communities, customers and infrastructure. | E30: Failure to manage material risks can result in business interruption, revenue loss, asset damage and higher risk costs. | F30: Risk + Opportunity | G30: Enterprise risk management, BCDMP, periodic mock exercises and integration of emerging risks into business planning. | H30: FY26 Integrated Annual Report | I30: 83 | J30: Tata Power Annual Report | K30: High | L30: =IFERROR(IF(INDEX(Benchmark!$K$33:$K$62,MATCH($A30,Benchmark!$A$33:$A$62,0))="n/a","No official equivalent",INDEX(Benchmark!$J$33:$J$62,MATCH($A30,Benchmark!$A$33:$A$62,0))&" - "&INDEX(Benchmark!$K$33:$K$62,MATCH($A30,Benchmark!$A$33:$A$62,0))),"") -> Risk management and BCDMP - High
A31: G05 | B31: Cybersecurity — Cyber Risk | C31: Tata Power identifies Digitalisation, Data Privacy and Cyber Security as a material topic. Increasing digitalisation of power generation, grids, smart meters and customer platforms increases cyber exposure. | D31: Cyber incidents can affect customers, employees, critical infrastructure and continuity of electricity services. | E31: Cyberattacks can result in operational disruption, financial losses, regulatory consequences, data breaches and reputational damage. | F31: Risk | G31: Information-security architecture, access controls, cybersecurity measures, awareness and protection of customer/operational data. | H31: FY26 BRSR / Integrated Annual Report | I31: 295; 82 | J31: Tata Power BRSR / Annual Report | K31: High | L31: =IFERROR(IF(INDEX(Benchmark!$K$33:$K$62,MATCH($A31,Benchmark!$A$33:$A$62,0))="n/a","No official equivalent",INDEX(Benchmark!$J$33:$J$62,MATCH($A31,Benchmark!$A$33:$A$62,0))&" - "&INDEX(Benchmark!$K$33:$K$62,MATCH($A31,Benchmark!$A$33:$A$62,0))),"") -> Digitalisation, data privacy and cyber security - Very High
A32: G06 | B32: Data Privacy — Customer Data | C32: Tata Power expanded its earlier digitalisation/cybersecurity topic to explicitly include Data Privacy in FY26, recognising the importance of protecting personal and operational data. | D32: Improper use or disclosure of personal data can directly affect customers, employees and other stakeholders. | E32: Data breaches can create regulatory penalties, remediation costs, customer loss and reputational damage. | F32: Risk | G32: Customer privacy controls, information-security framework and compliance with India's Digital Personal Data Protection Act, 2023. | H32: FY26 Integrated Annual Report | I32: 82 | J32: Tata Power Annual Report | K32: High | L32: =IFERROR(IF(INDEX(Benchmark!$K$33:$K$62,MATCH($A32,Benchmark!$A$33:$A$62,0))="n/a","No official equivalent",INDEX(Benchmark!$J$33:$J$62,MATCH($A32,Benchmark!$A$33:$A$62,0))&" - "&INDEX(Benchmark!$K$33:$K$62,MATCH($A32,Benchmark!$A$33:$A$62,0))),"") -> Digitalisation, data privacy and cyber security - Very High
A33: G07 | B33: Responsible Supply Chain — Supplier ESG | C33: Tata Power identifies Responsible Supply Chain as a material topic. Its supplier ESG framework considers environmental, social, ethical and country-specific risks and screens suppliers accordingly. | D33: Supply-chain practices can create impacts related to labour, human rights, environment, health & safety and responsible sourcing. | E33: Supplier failures can cause disruptions, quality issues, reputational damage and increased procurement costs. | F33: Risk + Opportunity | G33: ESG screening, supplier assessments, responsible supply-chain policy, supplier ESG awareness and development programmes. | H33: FY26 Integrated Annual Report / Tata Power Supplier ESG | I33: 82; Supplier section | J33: Tata Power Annual Report / Corporate website | K33: High | L33: =IFERROR(IF(INDEX(Benchmark!$K$33:$K$62,MATCH($A33,Benchmark!$A$33:$A$62,0))="n/a","No official equivalent",INDEX(Benchmark!$J$33:$J$62,MATCH($A33,Benchmark!$A$33:$A$62,0))&" - "&INDEX(Benchmark!$K$33:$K$62,MATCH($A33,Benchmark!$A$33:$A$62,0))),"") -> Responsible supply chain - High
A34: G08 | B34: Transparency — ESG Disclosure & Accountability | C34: Tata Power identifies Transparency and Accountability as a material governance topic. FY26 reporting includes integrated reporting, BRSR disclosures and enhanced ESG reporting. | D34: Transparent reporting supports stakeholder understanding, accountability and informed engagement. | E34: Weak transparency can reduce investor confidence and increase regulatory/reputational risk. | F34: Risk + Opportunity | G34: Integrated reporting, BRSR, assurance, stakeholder dialogue and enhanced ESG disclosures. | H34: FY26 Integrated Annual Report | I34: 82–83 | J34: Tata Power Annual Report | K34: High | L34: =IFERROR(IF(INDEX(Benchmark!$K$33:$K$62,MATCH($A34,Benchmark!$A$33:$A$62,0))="n/a","No official equivalent",INDEX(Benchmark!$J$33:$J$62,MATCH($A34,Benchmark!$A$33:$A$62,0))&" - "&INDEX(Benchmark!$K$33:$K$62,MATCH($A34,Benchmark!$A$33:$A$62,0))),"") -> Transparency and accountability - High
A35: G09 | B35: Innovation — Clean Technology | C35: Tata Power identifies Innovation and Collaborations as a material topic and highlights technologies such as CCUS, Green Hydrogen, SMR and other emerging solutions, along with collaboration with external technology partners. | D35: Clean-technology innovation can reduce environmental impacts and support the energy transition. | E35: Successful innovation can create new revenue streams and improve efficiency; failure to adapt can create technology and competitiveness risks. | F35: Risk + Opportunity | G35: Partnerships with startups, technology firms, academic institutions and other organisations; development/adoption of emerging clean technologies. | H35: FY26 Integrated Annual Report | I35: 83 | J35: Tata Power Annual Report | K35: High | L35: =IFERROR(IF(INDEX(Benchmark!$K$33:$K$62,MATCH($A35,Benchmark!$A$33:$A$62,0))="n/a","No official equivalent",INDEX(Benchmark!$J$33:$J$62,MATCH($A35,Benchmark!$A$33:$A$62,0))&" - "&INDEX(Benchmark!$K$33:$K$62,MATCH($A35,Benchmark!$A$33:$A$62,0))),"") -> Innovation and collaborations - High
A36: G10 | B36: Creating Economic Value | C36: For our independent DMA, this topic captures responsible economic conduct, value creation, capital allocation and tax-related stakeholder responsibilities. Tata Power's official FY26 material topic is Creating Economic Value; this topic is now labelled to match it (previously “Responsible Tax & Economic Conduct”). No tax-specific evidence was found in the sources reviewed (see Sources & Checks). | D36: Responsible economic conduct affects employees, suppliers, governments, investors and communities through value distribution and economic contribution. | E36: Efficient capital allocation and sustainable value creation influence long-term financial resilience and shareholder value. | F36: Opportunity + Risk | G36: Operational excellence, balance-sheet strengthening, efficient capital allocation and creation of economic value. | H36: FY26 Integrated Annual Report | I36: 82–83 | J36: Tata Power Annual Report | K36: High | L36: =IFERROR(IF(INDEX(Benchmark!$K$33:$K$62,MATCH($A36,Benchmark!$A$33:$A$62,0))="n/a","No official equivalent",INDEX(Benchmark!$J$33:$J$62,MATCH($A36,Benchmark!$A$33:$A$62,0))&" - "&INDEX(Benchmark!$K$33:$K$62,MATCH($A36,Benchmark!$A$33:$A$62,0))),"") -> Creating economic value - Very High

Sheet Scoring Methodology
A1: IMPACT SCORING METHODOLOGY
A3: Severity Score | B3: Classification | C3: Definition | E3: Likelihood factors
A4: 1 | B4: Very Low | C4: Minimal impact | E4: 1 | F4: 2 | G4: 3 | H4: 4 | I4: 5
A5: 2 | B5: Low | C5: Limited impact | E5: 0.6 | F5: 0.75 | G5: 0.85 | H5: 0.95 | I5: 1
A6: 3 | B6: Moderate | C6: Noticeable but manageable
A7: 4 | B7: High | C7: Significant stakeholder impact | E7: Inherent Impact = (Severity + Scope + Irremediability) / 3
A8: 5 | B8: Very High | C8: Severe/critical impact; potentially irreversible | E8: Impact Score = [(Severity + Scope + Irremediability) / 3] × Likelihood Factor
E10: Impact Score | F10: 1.00–1.99 | G10: 2.00–2.99 | H10: 3.00–3.99 | I10: 4.00–5.00
A11: Irremediability Score | B11: Classification | C11: Definition | E11: Classification | F11: Low | G11: Moderate | H11: High | I11: Very High
A12: 1 | B12: Easily Reversible | C12: Impact can be completely corrected quickly
A13: 2 | B13: Mostly Reversible | C13: Can be restored with limited intervention
A14: 3 | B14: Partially Reversible | C14: Restoration is possible but requires significant effort
A15: 4 | B15: Difficult to Reverse | C15: Restoration is difficult, costly or uncertain
A16: 5 | B16: Irreversible | C16: Cannot realistically be restored to the original condition
A18: Likelihood Score | B18: Classification | C18: Definition
A19: 1 | B19: Very Unlikely | C19: Remote possibility
A20: 2 | B20: Unlikely | C20: Could occur, but not expected
A21: 3 | B21: Possible | C21: Reasonably possible
A22: 4 | B22: Likely | C22: Expected to occur under normal/foreseeable conditions
A23: 5 | B23: Almost Certain | C23: Highly likely / ongoing or recurrent exposure
A25: Scope Score | B25: Classification | C25: Definition
A26: 1 | B26: Very Limited | C26: Single site / very small group
A27: 2 | B27: Limited | C27: One location or limited stakeholder group
A28: 3 | B28: Moderate | C28: Multiple sites or stakeholder groups
A29: 4 | B29: Wide | C29: Multiple regions / large stakeholder population
A30: 5 | B30: Very Wide / Systemic | C30: Enterprise-wide, national, value-chain or potentially global

Sheet Impact Scoring
A1: Tata Power — Double Materiality Assessment | Impact Materiality Scoring
A2: Impact Score = Average (Severity + Scope + Irremediability) × Likelihood Factor
A4: ID | B4: Category | C4: ESG Topic | D4: Impact Description | E4: Affected Stakeholders | F4: Severity | G4: Scope | H4: Irremediability | I4: Likelihood | J4: Impact Score | K4: Materiality | L4: Scoring Rationale | M4: Evidence Reference
A5: E01 | B5: Environmental | C5: Climate Change | D5: Thermal generation contributes to GHG emissions and climate-related impacts, while transition to cleaner energy affects the environmental footprint. | E5: Environment, Communities, Customers, Society | F5: 5 | G5: 5 | H5: 5 | I5: 5 | J5: =AVERAGE(F5:H5)*CHOOSE(I5,0.6,0.75,0.85,0.95,1) -> 5 | K5: =IF(J5>=4,"Very High",IF(J5>=3,"High",IF(J5>=2,"Moderate","Low"))) -> Very High | L5: Global-scale impact with potentially irreversible consequences and high likelihood. | M5: FY26 BRSR p.293
A6: E02 | B6: Environmental | C6: GHG Emissions | D6: Coal-based generation contributes materially to Scope 1 emissions and associated climate impacts. | E6: Environment, Communities, Society | F6: 5 | G6: 5 | H6: 5 | I6: 5 | J6: =AVERAGE(F6:H6)*CHOOSE(I6,0.6,0.75,0.85,0.95,1) -> 5 | K6: =IF(J6>=4,"Very High",IF(J6>=3,"High",IF(J6>=2,"Moderate","Low"))) -> Very High | L6: High severity, broad scope and long-term climate consequences. | M6: FY26 BRSR p.293
A7: E03 | B7: Environmental | C7: Energy Management | D7: Inefficient energy use can increase resource consumption and environmental footprint across operations. | E7: Environment, Customers, Communities | F7: 3 | G7: 4 | H7: 3 | I7: 5 | J7: =AVERAGE(F7:H7)*CHOOSE(I7,0.6,0.75,0.85,0.95,1) -> 3.3333333 | K7: =IF(J7>=4,"Very High",IF(J7>=3,"High",IF(J7>=2,"Moderate","Low"))) -> High | L7: Significant operational footprint and high relevance to a power-sector business. | M7: FY26 BRSR p.293
A8: E04 | B8: Environmental | C8: Air Pollution | D8: Thermal operations can generate SOx, NOx and particulate emissions affecting air quality. | E8: Employees, Communities, Environment | F8: 5 | G8: 4 | H8: 4 | I8: 4 | J8: =AVERAGE(F8:H8)*CHOOSE(I8,0.6,0.75,0.85,0.95,1) -> 4.1166667 | K8: =IF(J8>=4,"Very High",IF(J8>=3,"High",IF(J8>=2,"Moderate","Low"))) -> Very High | L8: Potentially severe health and environmental consequences with significant local exposure. | M8: FY26 BRSR p.293
A9: E05 | B9: Environmental | C9: Water & Effluent | D9: Thermal generation can require significant water withdrawal and consumption, particularly in water-stressed areas. | E9: Communities, Environment, Water Users | F9: 4 | G9: 4 | H9: 4 | I9: 4 | J9: =AVERAGE(F9:H9)*CHOOSE(I9,0.6,0.75,0.85,0.95,1) -> 3.8 | K9: =IF(J9>=4,"Very High",IF(J9>=3,"High",IF(J9>=2,"Moderate","Low"))) -> High | L9: Significant resource dependence and potential ecosystem/community impacts. | M9: FY26 BRSR p.294
A10: E06 | B10: Environmental | C10: Biodiversity | D10: Energy infrastructure and land-intensive projects can affect ecosystems, habitats and biodiversity. | E10: Environment, Communities | F10: 4 | G10: 4 | H10: 5 | I10: 3 | J10: =AVERAGE(F10:H10)*CHOOSE(I10,0.6,0.75,0.85,0.95,1) -> 3.6833333 | K10: =IF(J10>=4,"Very High",IF(J10>=3,"High",IF(J10>=2,"Moderate","Low"))) -> High | L10: Potentially difficult-to-reverse ecological impacts, although likelihood varies by project/location. | M10: FY26 Integrated Report
A11: E07 | B11: Environmental | C11: Waste Management | D11: Generation and disposal of operational and manufacturing waste can create environmental and community impacts. | E11: Environment, Communities, Workers | F11: 3 | G11: 4 | H11: 3 | I11: 4 | J11: =AVERAGE(F11:H11)*CHOOSE(I11,0.6,0.75,0.85,0.95,1) -> 3.1666667 | K11: =IF(J11>=4,"Very High",IF(J11>=3,"High",IF(J11>=2,"Moderate","Low"))) -> High | L11: Waste impacts can occur across multiple operations and require effective management. | M11: FY26 Integrated Report
A12: E08 | B12: Environmental | C12: Ash Management | D12: Coal-based operations generate fly ash and bottom ash requiring storage, transportation and beneficial utilisation. | E12: Communities, Environment, Workers | F12: 4 | G12: 4 | H12: 3 | I12: 4 | J12: =AVERAGE(F12:H12)*CHOOSE(I12,0.6,0.75,0.85,0.95,1) -> 3.4833333 | K12: =IF(J12>=4,"Very High",IF(J12>=3,"High",IF(J12>=2,"Moderate","Low"))) -> High | L12: Large-volume waste stream with potential land, air and water impacts. | M12: FY26 Integrated Report
A13: E09 | B13: Environmental | C13: Land Use | D13: Solar, wind and other infrastructure projects require land and may affect land use, ecosystems and local communities. | E13: Communities, Land Users, Environment | F13: 3 | G13: 4 | H13: 4 | I13: 3 | J13: =AVERAGE(F13:H13)*CHOOSE(I13,0.6,0.75,0.85,0.95,1) -> 3.1166667 | K13: =IF(J13>=4,"Very High",IF(J13>=3,"High",IF(J13>=2,"Moderate","Low"))) -> High | L13: Impacts can be geographically significant and difficult to reverse depending on project location. | M13: FY26 BRSR p.294
A14: E10 | B14: Environmental | C14: Resource Use & Circular Economy | D14: Use of materials and management of end-of-life equipment creates opportunities and impacts related to resource efficiency and circularity. | E14: Environment, Suppliers, Communities | F14: 3 | G14: 4 | H14: 3 | I14: 4 | J14: =AVERAGE(F14:H14)*CHOOSE(I14,0.6,0.75,0.85,0.95,1) -> 3.1666667 | K14: =IF(J14>=4,"Very High",IF(J14>=3,"High",IF(J14>=2,"Moderate","Low"))) -> High | L14: Resource consumption occurs across the value chain and circularity can reduce environmental pressure. | M14: FY26 Integrated Report
A15: S01 | B15: Social | C15: Occupational Health & Safety | D15: Generation, transmission, distribution and project activities expose workers to electrical, machinery, height and other occupational hazards. | E15: Employees, Workers, Contractors | F15: 5 | G15: 4 | H15: 5 | I15: 4 | J15: =AVERAGE(F15:H15)*CHOOSE(I15,0.6,0.75,0.85,0.95,1) -> 4.4333333 | K15: =IF(J15>=4,"Very High",IF(J15>=3,"High",IF(J15>=2,"Moderate","Low"))) -> Very High | L15: Potential for severe or fatal consequences; impacts can be irreversible. | M15: FY26 BRSR pp.294–295
A16: S02 | B16: Social | C16: Employee Health, Wellbeing & Engagement | D16: Employee physical, mental, social and financial wellbeing can be affected by workplace conditions and organisational practices. | E16: Employees, Families | F16: 3 | G16: 4 | H16: 3 | I16: 4 | J16: =AVERAGE(F16:H16)*CHOOSE(I16,0.6,0.75,0.85,0.95,1) -> 3.1666667 | K16: =IF(J16>=4,"Very High",IF(J16>=3,"High",IF(J16>=2,"Moderate","Low"))) -> High | L16: Broad workforce exposure with potential effects on wellbeing and quality of working life. | M16: FY26 Integrated Report — People
... A34: G10 | B34: Governance | C34: Creating Economic Value | D34: Economic value creation and responsible economic conduct influence employees, suppliers, governments, investors and communities. | E34: Employees, Suppliers, Government, Investors, Communities | F34: 3 | G34: 5 | H34: 3 | I34: 3 | J34: =AVERAGE(F34:H34)*CHOOSE(I34,0.6,0.75,0.85,0.95,1) -> 3.1166667 | K34: =IF(J34>=4,"Very High",IF(J34>=3,"High",IF(J34>=2,"Moderate","Low"))) -> High | L34: Broad stakeholder relevance but comparatively indirect impact on people and environment. | M34: FY26 Integrated Report pp.82–83

Sheet Financial Methodology
A1: FINANCIAL SCORING METHODOLOGY
A3: Likelihood factors | G3: Magnitude Score | H3: Classification | I3: Meaning
A4: 1 | B4: 2 | C4: 3 | D4: 4 | E4: 5 | G4: 1 | H4: Very Low | I4: Minimal financial effect; unlikely to meaningfully affect business performance
A5: 0.6 | B5: 0.75 | C5: 0.85 | D5: 0.95 | E5: 1 | G5: 2 | H5: Low | I5: Limited financial effect; manageable within normal operations
G6: 3 | H6: Moderate | I6: Could meaningfully affect a business unit, cost base, revenue or project economics
A7: Financial Score | B7: 1.00–1.99 | C7: 2.00–2.99 | D7: 3.00–3.99 | E7: 4.00–5.00 | G7: 4 | H7: High | I7: Could materially affect profitability, cash flows, assets, liabilities, capex or financing
A8: Classification | B8: Low | C8: Moderate | D8: High | E8: Very High | G8: 5 | H8: Very High | I8: Potentially major enterprise-level financial effect, including substantial asset impairment, revenue disruption or capital requirements
A11: Score | B11: Time Horizon | C11: Definition
A12: 1 | B12: Very Long Term | C12: >10 years
A13: 2 | B13: Long Term | C13: 5–10 years
A14: 3 | B14: Medium Term | C14: 3–5 years
A15: 4 | B15: Short Term | C15: 1–3 years
A16: 5 | B16: Immediate / Current | C16: <1 year / already occurring

Sheet Financial Scoring
A1: Tata Power — Financial Materiality Assessment
A2: Financial Scoring of ESG Topics | FY2025–26
A4: ID | B4: ESG Topic | C4: Magnitude | D4: Likelihood | E4: Time Horizon | F4: Financial Score | G4: Classification
A5: E01 | B5: Climate Change | C5: 5 | D5: 5 | E5: 3–5 years | F5: =C5*CHOOSE(D5,0.6,0.75,0.85,0.95,1) -> 5 | G5: =IF(F5>=4,"Very High",IF(F5>=3,"High",IF(F5>=2,"Moderate","Low"))) -> Very High
A6: E02 | B6: GHG Emissions | C6: 5 | D6: 5 | E6: 3–5 years | F6: =C6*CHOOSE(D6,0.6,0.75,0.85,0.95,1) -> 5 | G6: =IF(F6>=4,"Very High",IF(F6>=3,"High",IF(F6>=2,"Moderate","Low"))) -> Very High
A7: E03 | B7: Energy Management | C7: 4 | D7: 5 | E7: 1–3 years | F7: =C7*CHOOSE(D7,0.6,0.75,0.85,0.95,1) -> 4 | G7: =IF(F7>=4,"Very High",IF(F7>=3,"High",IF(F7>=2,"Moderate","Low"))) -> Very High
A8: E04 | B8: Air Pollution | C8: 4 | D8: 4 | E8: 1–3 years | F8: =C8*CHOOSE(D8,0.6,0.75,0.85,0.95,1) -> 3.8 | G8: =IF(F8>=4,"Very High",IF(F8>=3,"High",IF(F8>=2,"Moderate","Low"))) -> High
A9: E05 | B9: Water & Effluent | C9: 4 | D9: 4 | E9: 1–3 years | F9: =C9*CHOOSE(D9,0.6,0.75,0.85,0.95,1) -> 3.8 | G9: =IF(F9>=4,"Very High",IF(F9>=3,"High",IF(F9>=2,"Moderate","Low"))) -> High
A10: E06 | B10: Biodiversity | C10: 3 | D10: 3 | E10: 5–10 years | F10: =C10*CHOOSE(D10,0.6,0.75,0.85,0.95,1) -> 2.55 | G10: =IF(F10>=4,"Very High",IF(F10>=3,"High",IF(F10>=2,"Moderate","Low"))) -> Moderate
A11: E07 | B11: Waste Management | C11: 3 | D11: 4 | E11: 1–3 years | F11: =C11*CHOOSE(D11,0.6,0.75,0.85,0.95,1) -> 2.85 | G11: =IF(F11>=4,"Very High",IF(F11>=3,"High",IF(F11>=2,"Moderate","Low"))) -> Moderate
A12: E08 | B12: Ash Management | C12: 4 | D12: 4 | E12: 1–3 years | F12: =C12*CHOOSE(D12,0.6,0.75,0.85,0.95,1) -> 3.8 | G12: =IF(F12>=4,"Very High",IF(F12>=3,"High",IF(F12>=2,"Moderate","Low"))) -> High
A13: E09 | B13: Land Use | C13: 3 | D13: 3 | E13: 3–5 years | F13: =C13*CHOOSE(D13,0.6,0.75,0.85,0.95,1) -> 2.55 | G13: =IF(F13>=4,"Very High",IF(F13>=3,"High",IF(F13>=2,"Moderate","Low"))) -> Moderate
A14: E10 | B14: Resource Use & Circular Economy | C14: 3 | D14: 4 | E14: 3–5 years | F14: =C14*CHOOSE(D14,0.6,0.75,0.85,0.95,1) -> 2.85 | G14: =IF(F14>=4,"Very High",IF(F14>=3,"High",IF(F14>=2,"Moderate","Low"))) -> Moderate
A15: S01 | B15: Occupational Health & Safety | C15: 5 | D15: 4 | E15: 1–3 years | F15: =C15*CHOOSE(D15,0.6,0.75,0.85,0.95,1) -> 4.75 | G15: =IF(F15>=4,"Very High",IF(F15>=3,"High",IF(F15>=2,"Moderate","Low"))) -> Very High
A16: S02 | B16: Employee Health, Wellbeing & Engagement | C16: 3 | D16: 4 | E16: 1–3 years | F16: =C16*CHOOSE(D16,0.6,0.75,0.85,0.95,1) -> 2.85 | G16: =IF(F16>=4,"Very High",IF(F16>=3,"High",IF(F16>=2,"Moderate","Low"))) -> Moderate
... A34: G10 | B34: Creating Economic Value | C34: 4 | D34: 3 | E34: 1–3 years | F34: =C34*CHOOSE(D34,0.6,0.75,0.85,0.95,1) -> 3.4 | G34: =IF(F34>=4,"Very High",IF(F34>=3,"High",IF(F34>=2,"Moderate","Low"))) -> High

Sheet DMA Matrix
A1: Tata Power — Double Materiality Assessment
A2: Impact & Financial Materiality of ESG Topics | FY2025–26 | J2: Vertical Threshold | M2: Horizontal Threshold
J3: Financial X | K3: Impact Y | M3: Financial X | N3: Impact Y
A4: ID | B4: Category | C4: ESG Topic | D4: Impact Score | E4: Impact Materiality | F4: Financial Score | G4: Financial Materiality | H4: DMA Classification | J4: 3 | K4: 1 | M4: 1 | N4: 3
A5: E01 | B5: =INDEX('Impact Scoring'!$B:$B,MATCH($A5,'Impact Scoring'!$A:$A,0)) -> Environmental | C5: =INDEX('Impact Scoring'!$C:$C,MATCH($A5,'Impact Scoring'!$A:$A,0)) -> Climate Change | D5: =INDEX('Impact Scoring'!$J:$J,MATCH($A5,'Impact Scoring'!$A:$A,0)) -> 5 | E5: =INDEX('Impact Scoring'!$K:$K,MATCH($A5,'Impact Scoring'!$A:$A,0)) -> Very High | F5: =INDEX('Financial Scoring'!$F:$F,MATCH($A5,'Financial Scoring'!$A:$A,0)) -> 5 | G5: =INDEX('Financial Scoring'!$G:$G,MATCH($A5,'Financial Scoring'!$A:$A,0)) -> Very High | H5: =IF(AND(D5>=3,F5>=3),"Double Material", IF(D5>=3,"Impact Material", IF(F5>=3,"Financially Material","Below Threshold"))) -> Double Material | J5: 3 | K5: 5 | M5: 5 | N5: 3
A6: E02 | B6: =INDEX('Impact Scoring'!$B:$B,MATCH($A6,'Impact Scoring'!$A:$A,0)) -> Environmental | C6: =INDEX('Impact Scoring'!$C:$C,MATCH($A6,'Impact Scoring'!$A:$A,0)) -> GHG Emissions | D6: =INDEX('Impact Scoring'!$J:$J,MATCH($A6,'Impact Scoring'!$A:$A,0)) -> 5 | E6: =INDEX('Impact Scoring'!$K:$K,MATCH($A6,'Impact Scoring'!$A:$A,0)) -> Very High | F6: =INDEX('Financial Scoring'!$F:$F,MATCH($A6,'Financial Scoring'!$A:$A,0)) -> 5 | G6: =INDEX('Financial Scoring'!$G:$G,MATCH($A6,'Financial Scoring'!$A:$A,0)) -> Very High | H6: =IF(AND(D6>=3,F6>=3),"Double Material", IF(D6>=3,"Impact Material", IF(F6>=3,"Financially Material","Below Threshold"))) -> Double Material
A7: E03 | B7: =INDEX('Impact Scoring'!$B:$B,MATCH($A7,'Impact Scoring'!$A:$A,0)) -> Environmental | C7: =INDEX('Impact Scoring'!$C:$C,MATCH($A7,'Impact Scoring'!$A:$A,0)) -> Energy Management | D7: =INDEX('Impact Scoring'!$J:$J,MATCH($A7,'Impact Scoring'!$A:$A,0)) -> 3.3333333 | E7: =INDEX('Impact Scoring'!$K:$K,MATCH($A7,'Impact Scoring'!$A:$A,0)) -> High | F7: =INDEX('Financial Scoring'!$F:$F,MATCH($A7,'Financial Scoring'!$A:$A,0)) -> 4 | G7: =INDEX('Financial Scoring'!$G:$G,MATCH($A7,'Financial Scoring'!$A:$A,0)) -> Very High | H7: =IF(AND(D7>=3,F7>=3),"Double Material", IF(D7>=3,"Impact Material", IF(F7>=3,"Financially Material","Below Threshold"))) -> Double Material | J7: Classification | K7: Number of Topics | M7: DMA Classification
A8: E04 | B8: =INDEX('Impact Scoring'!$B:$B,MATCH($A8,'Impact Scoring'!$A:$A,0)) -> Environmental | C8: =INDEX('Impact Scoring'!$C:$C,MATCH($A8,'Impact Scoring'!$A:$A,0)) -> Air Pollution | D8: =INDEX('Impact Scoring'!$J:$J,MATCH($A8,'Impact Scoring'!$A:$A,0)) -> 4.1166667 | E8: =INDEX('Impact Scoring'!$K:$K,MATCH($A8,'Impact Scoring'!$A:$A,0)) -> Very High | F8: =INDEX('Financial Scoring'!$F:$F,MATCH($A8,'Financial Scoring'!$A:$A,0)) -> 3.8 | G8: =INDEX('Financial Scoring'!$G:$G,MATCH($A8,'Financial Scoring'!$A:$A,0)) -> High | H8: =IF(AND(D8>=3,F8>=3),"Double Material", IF(D8>=3,"Impact Material", IF(F8>=3,"Financially Material","Below Threshold"))) -> Double Material | J8: Double Material | K8: =COUNTIF(H5:H34,"Double Material") -> 22 | M8: Impact | N8: Financial | O8: Classification
A9: E05 | B9: =INDEX('Impact Scoring'!$B:$B,MATCH($A9,'Impact Scoring'!$A:$A,0)) -> Environmental | C9: =INDEX('Impact Scoring'!$C:$C,MATCH($A9,'Impact Scoring'!$A:$A,0)) -> Water & Effluent | D9: =INDEX('Impact Scoring'!$J:$J,MATCH($A9,'Impact Scoring'!$A:$A,0)) -> 3.8 | E9: =INDEX('Impact Scoring'!$K:$K,MATCH($A9,'Impact Scoring'!$A:$A,0)) -> High | F9: =INDEX('Financial Scoring'!$F:$F,MATCH($A9,'Financial Scoring'!$A:$A,0)) -> 3.8 | G9: =INDEX('Financial Scoring'!$G:$G,MATCH($A9,'Financial Scoring'!$A:$A,0)) -> High | H9: =IF(AND(D9>=3,F9>=3),"Double Material", IF(D9>=3,"Impact Material", IF(F9>=3,"Financially Material","Below Threshold"))) -> Double Material | J9: Impact Material | K9: =COUNTIF(H5:H34,"Impact Material") -> 7 | M9: ≥ 3.00 | N9: ≥ 3.00 | O9: Double Material
A10: E06 | B10: =INDEX('Impact Scoring'!$B:$B,MATCH($A10,'Impact Scoring'!$A:$A,0)) -> Environmental | C10: =INDEX('Impact Scoring'!$C:$C,MATCH($A10,'Impact Scoring'!$A:$A,0)) -> Biodiversity | D10: =INDEX('Impact Scoring'!$J:$J,MATCH($A10,'Impact Scoring'!$A:$A,0)) -> 3.6833333 | E10: =INDEX('Impact Scoring'!$K:$K,MATCH($A10,'Impact Scoring'!$A:$A,0)) -> High | F10: =INDEX('Financial Scoring'!$F:$F,MATCH($A10,'Financial Scoring'!$A:$A,0)) -> 2.55 | G10: =INDEX('Financial Scoring'!$G:$G,MATCH($A10,'Financial Scoring'!$A:$A,0)) -> Moderate | H10: =IF(AND(D10>=3,F10>=3),"Double Material", IF(D10>=3,"Impact Material", IF(F10>=3,"Financially Material","Below Threshold"))) -> Impact Material | J10: Financially Material | K10: =COUNTIF(H5:H34,"Financially Material") -> 1 | M10: ≥ 3.00 | N10: < 3.00 | O10: Impact Material
A11: E07 | B11: =INDEX('Impact Scoring'!$B:$B,MATCH($A11,'Impact Scoring'!$A:$A,0)) -> Environmental | C11: =INDEX('Impact Scoring'!$C:$C,MATCH($A11,'Impact Scoring'!$A:$A,0)) -> Waste Management | D11: =INDEX('Impact Scoring'!$J:$J,MATCH($A11,'Impact Scoring'!$A:$A,0)) -> 3.1666667 | E11: =INDEX('Impact Scoring'!$K:$K,MATCH($A11,'Impact Scoring'!$A:$A,0)) -> High | F11: =INDEX('Financial Scoring'!$F:$F,MATCH($A11,'Financial Scoring'!$A:$A,0)) -> 2.85 | G11: =INDEX('Financial Scoring'!$G:$G,MATCH($A11,'Financial Scoring'!$A:$A,0)) -> Moderate | H11: =IF(AND(D11>=3,F11>=3),"Double Material", IF(D11>=3,"Impact Material", IF(F11>=3,"Financially Material","Below Threshold"))) -> Impact Material | J11: Below Threshold | K11: =COUNTIF(H5:H34,"Below Threshold") -> 0 | M11: < 3.00 | N11: ≥ 3.00 | O11: Financially Material
A12: E08 | B12: =INDEX('Impact Scoring'!$B:$B,MATCH($A12,'Impact Scoring'!$A:$A,0)) -> Environmental | C12: =INDEX('Impact Scoring'!$C:$C,MATCH($A12,'Impact Scoring'!$A:$A,0)) -> Ash Management | D12: =INDEX('Impact Scoring'!$J:$J,MATCH($A12,'Impact Scoring'!$A:$A,0)) -> 3.4833333 | E12: =INDEX('Impact Scoring'!$K:$K,MATCH($A12,'Impact Scoring'!$A:$A,0)) -> High | F12: =INDEX('Financial Scoring'!$F:$F,MATCH($A12,'Financial Scoring'!$A:$A,0)) -> 3.8 | G12: =INDEX('Financial Scoring'!$G:$G,MATCH($A12,'Financial Scoring'!$A:$A,0)) -> High | H12: =IF(AND(D12>=3,F12>=3),"Double Material", IF(D12>=3,"Impact Material", IF(F12>=3,"Financially Material","Below Threshold"))) -> Double Material | M12: < 3.00 | N12: < 3.00 | O12: Below Threshold
A13: E09 | B13: =INDEX('Impact Scoring'!$B:$B,MATCH($A13,'Impact Scoring'!$A:$A,0)) -> Environmental | C13: =INDEX('Impact Scoring'!$C:$C,MATCH($A13,'Impact Scoring'!$A:$A,0)) -> Land Use | D13: =INDEX('Impact Scoring'!$J:$J,MATCH($A13,'Impact Scoring'!$A:$A,0)) -> 3.1166667 | E13: =INDEX('Impact Scoring'!$K:$K,MATCH($A13,'Impact Scoring'!$A:$A,0)) -> High | F13: =INDEX('Financial Scoring'!$F:$F,MATCH($A13,'Financial Scoring'!$A:$A,0)) -> 2.55 | G13: =INDEX('Financial Scoring'!$G:$G,MATCH($A13,'Financial Scoring'!$A:$A,0)) -> Moderate | H13: =IF(AND(D13>=3,F13>=3),"Double Material", IF(D13>=3,"Impact Material", IF(F13>=3,"Financially Material","Below Threshold"))) -> Impact Material
A14: E10 | B14: =INDEX('Impact Scoring'!$B:$B,MATCH($A14,'Impact Scoring'!$A:$A,0)) -> Environmental | C14: =INDEX('Impact Scoring'!$C:$C,MATCH($A14,'Impact Scoring'!$A:$A,0)) -> Resource Use & Circular Economy | D14: =INDEX('Impact Scoring'!$J:$J,MATCH($A14,'Impact Scoring'!$A:$A,0)) -> 3.1666667 | E14: =INDEX('Impact Scoring'!$K:$K,MATCH($A14,'Impact Scoring'!$A:$A,0)) -> High | F14: =INDEX('Financial Scoring'!$F:$F,MATCH($A14,'Financial Scoring'!$A:$A,0)) -> 2.85 | G14: =INDEX('Financial Scoring'!$G:$G,MATCH($A14,'Financial Scoring'!$A:$A,0)) -> Moderate | H14: =IF(AND(D14>=3,F14>=3),"Double Material", IF(D14>=3,"Impact Material", IF(F14>=3,"Financially Material","Below Threshold"))) -> Impact Material
A15: S01 | B15: =INDEX('Impact Scoring'!$B:$B,MATCH($A15,'Impact Scoring'!$A:$A,0)) -> Social | C15: =INDEX('Impact Scoring'!$C:$C,MATCH($A15,'Impact Scoring'!$A:$A,0)) -> Occupational Health & Safety | D15: =INDEX('Impact Scoring'!$J:$J,MATCH($A15,'Impact Scoring'!$A:$A,0)) -> 4.4333333 | E15: =INDEX('Impact Scoring'!$K:$K,MATCH($A15,'Impact Scoring'!$A:$A,0)) -> Very High | F15: =INDEX('Financial Scoring'!$F:$F,MATCH($A15,'Financial Scoring'!$A:$A,0)) -> 4.75 | G15: =INDEX('Financial Scoring'!$G:$G,MATCH($A15,'Financial Scoring'!$A:$A,0)) -> Very High | H15: =IF(AND(D15>=3,F15>=3),"Double Material", IF(D15>=3,"Impact Material", IF(F15>=3,"Financially Material","Below Threshold"))) -> Double Material
A16: S02 | B16: =INDEX('Impact Scoring'!$B:$B,MATCH($A16,'Impact Scoring'!$A:$A,0)) -> Social | C16: =INDEX('Impact Scoring'!$C:$C,MATCH($A16,'Impact Scoring'!$A:$A,0)) -> Employee Health, Wellbeing & Engagement | D16: =INDEX('Impact Scoring'!$J:$J,MATCH($A16,'Impact Scoring'!$A:$A,0)) -> 3.1666667 | E16: =INDEX('Impact Scoring'!$K:$K,MATCH($A16,'Impact Scoring'!$A:$A,0)) -> High | F16: =INDEX('Financial Scoring'!$F:$F,MATCH($A16,'Financial Scoring'!$A:$A,0)) -> 2.85 | G16: =INDEX('Financial Scoring'!$G:$G,MATCH($A16,'Financial Scoring'!$A:$A,0)) -> Moderate | H16: =IF(AND(D16>=3,F16>=3),"Double Material", IF(D16>=3,"Impact Material", IF(F16>=3,"Financially Material","Below Threshold"))) -> Impact Material
A17: S03 | B17: =INDEX('Impact Scoring'!$B:$B,MATCH($A17,'Impact Scoring'!$A:$A,0)) -> Social | C17: =INDEX('Impact Scoring'!$C:$C,MATCH($A17,'Impact Scoring'!$A:$A,0)) -> Diversity & Inclusion | D17: =INDEX('Impact Scoring'!$J:$J,MATCH($A17,'Impact Scoring'!$A:$A,0)) -> 3.1666667 | E17: =INDEX('Impact Scoring'!$K:$K,MATCH($A17,'Impact Scoring'!$A:$A,0)) -> High | F17: =INDEX('Financial Scoring'!$F:$F,MATCH($A17,'Financial Scoring'!$A:$A,0)) -> 2.85 | G17: =INDEX('Financial Scoring'!$G:$G,MATCH($A17,'Financial Scoring'!$A:$A,0)) -> Moderate | H17: =IF(AND(D17>=3,F17>=3),"Double Material", IF(D17>=3,"Impact Material", IF(F17>=3,"Financially Material","Below Threshold"))) -> Impact Material
A18: S04 | B18: =INDEX('Impact Scoring'!$B:$B,MATCH($A18,'Impact Scoring'!$A:$A,0)) -> Social | C18: =INDEX('Impact Scoring'!$C:$C,MATCH($A18,'Impact Scoring'!$A:$A,0)) -> Talent Development | D18: =INDEX('Impact Scoring'!$J:$J,MATCH($A18,'Impact Scoring'!$A:$A,0)) -> 2.85 | E18: =INDEX('Impact Scoring'!$K:$K,MATCH($A18,'Impact Scoring'!$A:$A,0)) -> Moderate | F18: =INDEX('Financial Scoring'!$F:$F,MATCH($A18,'Financial Scoring'!$A:$A,0)) -> 3.8 | G18: =INDEX('Financial Scoring'!$G:$G,MATCH($A18,'Financial Scoring'!$A:$A,0)) -> High | H18: =IF(AND(D18>=3,F18>=3),"Double Material", IF(D18>=3,"Impact Material", IF(F18>=3,"Financially Material","Below Threshold"))) -> Financially Material
A19: S05 | B19: =INDEX('Impact Scoring'!$B:$B,MATCH($A19,'Impact Scoring'!$A:$A,0)) -> Social | C19: =INDEX('Impact Scoring'!$C:$C,MATCH($A19,'Impact Scoring'!$A:$A,0)) -> Labour Relations & Working Conditions | D19: =INDEX('Impact Scoring'!$J:$J,MATCH($A19,'Impact Scoring'!$A:$A,0)) -> 3.4 | E19: =INDEX('Impact Scoring'!$K:$K,MATCH($A19,'Impact Scoring'!$A:$A,0)) -> High | F19: =INDEX('Financial Scoring'!$F:$F,MATCH($A19,'Financial Scoring'!$A:$A,0)) -> 3.4 | G19: =INDEX('Financial Scoring'!$G:$G,MATCH($A19,'Financial Scoring'!$A:$A,0)) -> High | H19: =IF(AND(D19>=3,F19>=3),"Double Material", IF(D19>=3,"Impact Material", IF(F19>=3,"Financially Material","Below Threshold"))) -> Double Material
A20: S06 | B20: =INDEX('Impact Scoring'!$B:$B,MATCH($A20,'Impact Scoring'!$A:$A,0)) -> Social | C20: =INDEX('Impact Scoring'!$C:$C,MATCH($A20,'Impact Scoring'!$A:$A,0)) -> Human Rights | D20: =INDEX('Impact Scoring'!$J:$J,MATCH($A20,'Impact Scoring'!$A:$A,0)) -> 3.9666667 | E20: =INDEX('Impact Scoring'!$K:$K,MATCH($A20,'Impact Scoring'!$A:$A,0)) -> High | F20: =INDEX('Financial Scoring'!$F:$F,MATCH($A20,'Financial Scoring'!$A:$A,0)) -> 3.4 | G20: =INDEX('Financial Scoring'!$G:$G,MATCH($A20,'Financial Scoring'!$A:$A,0)) -> High | H20: =IF(AND(D20>=3,F20>=3),"Double Material", IF(D20>=3,"Impact Material", IF(F20>=3,"Financially Material","Below Threshold"))) -> Double Material
A21: S07 | B21: =INDEX('Impact Scoring'!$B:$B,MATCH($A21,'Impact Scoring'!$A:$A,0)) -> Social | C21: =INDEX('Impact Scoring'!$C:$C,MATCH($A21,'Impact Scoring'!$A:$A,0)) -> Community Impact | D21: =INDEX('Impact Scoring'!$J:$J,MATCH($A21,'Impact Scoring'!$A:$A,0)) -> 4.1166667 | E21: =INDEX('Impact Scoring'!$K:$K,MATCH($A21,'Impact Scoring'!$A:$A,0)) -> Very High | F21: =INDEX('Financial Scoring'!$F:$F,MATCH($A21,'Financial Scoring'!$A:$A,0)) -> 3.4 | G21: =INDEX('Financial Scoring'!$G:$G,MATCH($A21,'Financial Scoring'!$A:$A,0)) -> High | H21: =IF(AND(D21>=3,F21>=3),"Double Material", IF(D21>=3,"Impact Material", IF(F21>=3,"Financially Material","Below Threshold"))) -> Double Material
A22: S08 | B22: =INDEX('Impact Scoring'!$B:$B,MATCH($A22,'Impact Scoring'!$A:$A,0)) -> Social | C22: =INDEX('Impact Scoring'!$C:$C,MATCH($A22,'Impact Scoring'!$A:$A,0)) -> Access & Affordability | D22: =INDEX('Impact Scoring'!$J:$J,MATCH($A22,'Impact Scoring'!$A:$A,0)) -> 4.1166667 | E22: =INDEX('Impact Scoring'!$K:$K,MATCH($A22,'Impact Scoring'!$A:$A,0)) -> Very High | F22: =INDEX('Financial Scoring'!$F:$F,MATCH($A22,'Financial Scoring'!$A:$A,0)) -> 4.75 | G22: =INDEX('Financial Scoring'!$G:$G,MATCH($A22,'Financial Scoring'!$A:$A,0)) -> Very High | H22: =IF(AND(D22>=3,F22>=3),"Double Material", IF(D22>=3,"Impact Material", IF(F22>=3,"Financially Material","Below Threshold"))) -> Double Material
A23: S09 | B23: =INDEX('Impact Scoring'!$B:$B,MATCH($A23,'Impact Scoring'!$A:$A,0)) -> Social | C23: =INDEX('Impact Scoring'!$C:$C,MATCH($A23,'Impact Scoring'!$A:$A,0)) -> Customer Service & Consumer Protection | D23: =INDEX('Impact Scoring'!$J:$J,MATCH($A23,'Impact Scoring'!$A:$A,0)) -> 3.4833333 | E23: =INDEX('Impact Scoring'!$K:$K,MATCH($A23,'Impact Scoring'!$A:$A,0)) -> High | F23: =INDEX('Financial Scoring'!$F:$F,MATCH($A23,'Financial Scoring'!$A:$A,0)) -> 3.8 | G23: =INDEX('Financial Scoring'!$G:$G,MATCH($A23,'Financial Scoring'!$A:$A,0)) -> High | H23: =IF(AND(D23>=3,F23>=3),"Double Material", IF(D23>=3,"Impact Material", IF(F23>=3,"Financially Material","Below Threshold"))) -> Double Material
A24: S10 | B24: =INDEX('Impact Scoring'!$B:$B,MATCH($A24,'Impact Scoring'!$A:$A,0)) -> Social | C24: =INDEX('Impact Scoring'!$C:$C,MATCH($A24,'Impact Scoring'!$A:$A,0)) -> Energy Reliability | D24: =INDEX('Impact Scoring'!$J:$J,MATCH($A24,'Impact Scoring'!$A:$A,0)) -> 4.4333333 | E24: =INDEX('Impact Scoring'!$K:$K,MATCH($A24,'Impact Scoring'!$A:$A,0)) -> Very High | F24: =INDEX('Financial Scoring'!$F:$F,MATCH($A24,'Financial Scoring'!$A:$A,0)) -> 5 | G24: =INDEX('Financial Scoring'!$G:$G,MATCH($A24,'Financial Scoring'!$A:$A,0)) -> Very High | H24: =IF(AND(D24>=3,F24>=3),"Double Material", IF(D24>=3,"Impact Material", IF(F24>=3,"Financially Material","Below Threshold"))) -> Double Material
... A34: G10 | B34: =INDEX('Impact Scoring'!$B:$B,MATCH($A34,'Impact Scoring'!$A:$A,0)) -> Governance | C34: =INDEX('Impact Scoring'!$C:$C,MATCH($A34,'Impact Scoring'!$A:$A,0)) -> Creating Economic Value | D34: =INDEX('Impact Scoring'!$J:$J,MATCH($A34,'Impact Scoring'!$A:$A,0)) -> 3.1166667 | E34: =INDEX('Impact Scoring'!$K:$K,MATCH($A34,'Impact Scoring'!$A:$A,0)) -> High | F34: =INDEX('Financial Scoring'!$F:$F,MATCH($A34,'Financial Scoring'!$A:$A,0)) -> 3.4 | G34: =INDEX('Financial Scoring'!$G:$G,MATCH($A34,'Financial Scoring'!$A:$A,0)) -> High | H34: =IF(AND(D34>=3,F34>=3),"Double Material", IF(D34>=3,"Impact Material", IF(F34>=3,"Financially Material","Below Threshold"))) -> Double Material

Sheet IRO & Recommendations
A1: Tata Power — IRO & Strategic Recommendations
A2: Impacts, Risks & Opportunities arising from Double Materiality Assessment | FY2025–26
A4: ID | B4: ESG Topic | C4: DMA | D4: Material IRO | E4: IRO Type | F4: Strategic Recommendation | G4: Suggested KPI | H4: Priority
A5: E01 | B5: Climate Change | C5: =INDEX('DMA Matrix'!$H$5:$H$34,MATCH($A5,'DMA Matrix'!$A$5:$A$34,0)) -> Double Material | D5: Climate transition and physical climate risks affecting operations and stakeholders | E5: Impact + Risk + Opportunity | F5: Develop a climate transition roadmap and integrate physical and transition climate risks into business and capital planning. | G5: Scope 1 & 2 emissions; renewable capacity %; climate-risk assessed assets | H5: Critical | J5: IRO Type | K5: Meaning
A6: E02 | B6: GHG Emissions | C6: =INDEX('DMA Matrix'!$H$5:$H$34,MATCH($A6,'DMA Matrix'!$A$5:$A$34,0)) -> Double Material | D6: GHG emissions from operations and value chain contributing to climate change | E6: Impact + Risk | F6: Strengthen Scope 1, 2 and 3 measurement and implement asset-level emissions reduction pathways. | G6: Scope 1/2/3 emissions; emissions intensity | H6: Critical | J6: Impact | K6: Actual or potential positive/negative effect on people or environment
A7: E03 | B7: Energy Management | C7: =INDEX('DMA Matrix'!$H$5:$H$34,MATCH($A7,'DMA Matrix'!$A$5:$A$34,0)) -> Double Material | D7: Energy consumption and efficiency of power operations | E7: Impact + Risk + Opportunity | F7: Scale energy-efficiency initiatives, digital monitoring and renewable-energy sourcing across operations. | G7: Energy intensity; renewable energy % | H7: High | J7: Risk | K7: ESG-related factor that could negatively affect Tata Power's financial position/performance
A8: E04 | B8: Air Pollution | C8: =INDEX('DMA Matrix'!$H$5:$H$34,MATCH($A8,'DMA Matrix'!$A$5:$A$34,0)) -> Double Material | D8: SOx, NOx, particulate matter and other operational emissions | E8: Impact + Risk | F8: Strengthen emissions monitoring and pollution-control systems across relevant generating assets. | G8: SOx/NOx/PM emissions; compliance rate | H8: High | J8: Opportunity | K8: ESG-related factor that could create business, financial or strategic value
A9: E05 | B9: Water & Effluent | C9: =INDEX('DMA Matrix'!$H$5:$H$34,MATCH($A9,'DMA Matrix'!$A$5:$A$34,0)) -> Double Material | D9: Water withdrawal, consumption and discharge affecting water resources | E9: Impact + Risk | F9: Implement water stewardship plans, recycling/reuse systems and water-risk assessments at high-risk locations. | G9: Water withdrawal; water intensity; reuse % | H9: High | J9: Impact + Risk | K9: Material impact with corresponding financial risk
A10: E06 | B10: Biodiversity | C10: =INDEX('DMA Matrix'!$H$5:$H$34,MATCH($A10,'DMA Matrix'!$A$5:$A$34,0)) -> Impact Material | D10: Potential ecosystem and habitat impacts from infrastructure and operations | E10: Impact + Risk | F10: Integrate biodiversity screening, mitigation hierarchy and restoration planning into project development. | G10: Sites screened; biodiversity mitigation/restoration | H10: Medium | J10: Impact + Opportunity | K10: Material impact with corresponding business opportunity
A11: E07 | B11: Waste Management | C11: =INDEX('DMA Matrix'!$H$5:$H$34,MATCH($A11,'DMA Matrix'!$A$5:$A$34,0)) -> Impact Material | D11: Generation, disposal and treatment of operational waste | E11: Impact + Risk + Opportunity | F11: Increase segregation, recycling, resource recovery and circularity across operations. | G11: Waste generated; recycling/recovery % | H11: Medium | J11: Impact + Risk + Opportunity | K11: Material impact with both financial risk and opportunity
A12: E08 | B12: Ash Management | C12: =INDEX('DMA Matrix'!$H$5:$H$34,MATCH($A12,'DMA Matrix'!$A$5:$A$34,0)) -> Double Material | D12: Environmental and community impacts from fly ash and bottom ash | E12: Impact + Risk + Opportunity | F12: Increase beneficial ash utilisation while strengthening storage, transportation and disposal controls. | G12: Ash utilisation %; ash generated | H12: High
A13: E09 | B13: Land Use | C13: =INDEX('DMA Matrix'!$H$5:$H$34,MATCH($A13,'DMA Matrix'!$A$5:$A$34,0)) -> Impact Material | D13: Land footprint and associated local environmental impacts | E13: Impact + Risk | F13: Strengthen land-impact assessment and mitigation during project planning and operations. | G13: Land footprint; area restored/rehabilitated | H13: Medium | J13: Priority | K13: Definition
A14: E10 | B14: Resource Use & Circular Economy | C14: =INDEX('DMA Matrix'!$H$5:$H$34,MATCH($A14,'DMA Matrix'!$A$5:$A$34,0)) -> Impact Material | D14: Resource consumption and opportunities for material circularity | E14: Impact + Opportunity | F14: Integrate circular-economy principles into procurement, operations and end-of-life management. | G14: Recycled/reused material %; resource intensity | H14: Medium | J14: Critical | K14: Double Material + very high impact/financial exposure or direct business continuity/strategic significance
A15: S01 | B15: Occupational Health & Safety | C15: =INDEX('DMA Matrix'!$H$5:$H$34,MATCH($A15,'DMA Matrix'!$A$5:$A$34,0)) -> Double Material | D15: Workplace injuries, fatalities and unsafe working conditions | E15: Impact + Risk | F15: Strengthen contractor safety governance, predictive safety systems, training and near-miss reporting. | G15: LTIFR; fatalities; near-miss reporting | H15: Critical | J15: High | K15: Double Material with material impact and financial exposure, but comparatively lower urgency/scale
A16: S02 | B16: Employee Health, Wellbeing & Engagement | C16: =INDEX('DMA Matrix'!$H$5:$H$34,MATCH($A16,'DMA Matrix'!$A$5:$A$34,0)) -> Impact Material | D16: Employee wellbeing, engagement and workforce experience | E16: Impact + Opportunity | F16: Strengthen employee listening, wellbeing programmes and engagement mechanisms across the workforce. | G16: Engagement score; wellbeing participation | H16: Medium | J16: Medium | K16: Impact Material topics where stakeholder/environmental impact is material but financial exposure is below threshold
A17: S03 | B17: Diversity & Inclusion | C17: =INDEX('DMA Matrix'!$H$5:$H$34,MATCH($A17,'DMA Matrix'!$A$5:$A$34,0)) -> Impact Material | D17: Workforce diversity, inclusion and equal opportunity | E17: Impact + Opportunity | F17: Strengthen diverse talent pipelines, inclusive leadership and representation initiatives. | G17: Women workforce %; women leadership %; inclusion score | H17: Medium | J17: Monitor | K17: Below Threshold topics
A18: S04 | B18: Talent Development | C18: =INDEX('DMA Matrix'!$H$5:$H$34,MATCH($A18,'DMA Matrix'!$A$5:$A$34,0)) -> Financially Material | D18: Skills gaps and future capability requirements affecting business performance | E18: Risk + Opportunity | F18: Build future-skills programmes covering renewable energy, digitalisation, technology and sustainability capabilities. | G18: Training hours; critical-skill coverage; internal mobility | H18: High
A19: S05 | B19: Labour Relations & Working Conditions | C19: =INDEX('DMA Matrix'!$H$5:$H$34,MATCH($A19,'DMA Matrix'!$A$5:$A$34,0)) -> Double Material | D19: Working conditions, labour relations and workforce practices | E19: Impact + Risk | F19: Strengthen grievance mechanisms, workforce engagement and monitoring of working conditions across operations and contractors. | G19: Grievance resolution rate; workforce assessment coverage | H19: High
A20: S06 | B20: Human Rights | C20: =INDEX('DMA Matrix'!$H$5:$H$34,MATCH($A20,'DMA Matrix'!$A$5:$A$34,0)) -> Double Material | D20: Potential human-rights impacts across operations and supply chain | E20: Impact + Risk | F20: Strengthen human-rights due diligence, supplier screening and grievance mechanisms. | G20: Human-rights assessments; supplier screening % | H20: High
A21: S07 | B21: Community Impact | C21: =INDEX('DMA Matrix'!$H$5:$H$34,MATCH($A21,'DMA Matrix'!$A$5:$A$34,0)) -> Double Material | D21: Effects of power projects and operations on surrounding communities | E21: Impact + Risk + Opportunity | F21: Implement structured community-impact assessments and strengthen stakeholder engagement around projects. | G21: Community beneficiaries; grievances resolved; CSR investment | H21: High
A22: S08 | B22: Access & Affordability | C22: =INDEX('DMA Matrix'!$H$5:$H$34,MATCH($A22,'DMA Matrix'!$A$5:$A$34,0)) -> Double Material | D22: Access to reliable and affordable electricity for consumers and communities | E22: Impact + Risk + Opportunity | F22: Expand affordable clean-energy solutions and programmes supporting underserved customer segments. | G22: Customers served; access/affordability metrics | H22: Critical
A23: S09 | B23: Customer Service & Consumer Protection | C23: =INDEX('DMA Matrix'!$H$5:$H$34,MATCH($A23,'DMA Matrix'!$A$5:$A$34,0)) -> Double Material | D23: Customer experience, complaints and consumer protection | E23: Impact + Risk | F23: Strengthen service responsiveness, grievance resolution and consumer-protection mechanisms. | G23: Complaint resolution time; customer satisfaction | H23: High
A24: S10 | B24: Energy Reliability | C24: =INDEX('DMA Matrix'!$H$5:$H$34,MATCH($A24,'DMA Matrix'!$A$5:$A$34,0)) -> Double Material | D24: Reliability and continuity of electricity supply | E24: Impact + Risk | F24: Invest in grid resilience, predictive maintenance and digital monitoring to improve reliability. | G24: SAIDI/SAIFI; outage duration; reliability rate | H24: Critical
A25: G01 | B25: Business Ethics — Anti-corruption | C25: =INDEX('DMA Matrix'!$H$5:$H$34,MATCH($A25,'DMA Matrix'!$A$5:$A$34,0)) -> Double Material | D25: Corruption, bribery and unethical conduct risks | E25: Risk | F25: Strengthen ethics training, third-party due diligence, whistleblower mechanisms and monitoring. | G25: Ethics training %; substantiated cases; third-party screening % | H25: High
A26: G02 | B26: Regulatory Compliance | C26: =INDEX('DMA Matrix'!$H$5:$H$34,MATCH($A26,'DMA Matrix'!$A$5:$A$34,0)) -> Double Material | D26: Non-compliance with environmental, safety and sector regulations | E26: Risk | F26: Strengthen regulatory monitoring, compliance controls and accountability for obligations. | G26: Compliance rate; regulatory incidents | H26: Critical
A27: G03 | B27: ESG Governance | C27: =INDEX('DMA Matrix'!$H$5:$H$34,MATCH($A27,'DMA Matrix'!$A$5:$A$34,0)) -> Double Material | D27: ESG oversight, accountability and integration into decision-making | E27: Risk + Opportunity | F27: Strengthen Board-level ESG oversight and management accountability for material ESG objectives. | G27: Board ESG reviews; ESG targets linked to accountability | H27: High
A28: G04 | B28: Risk Management — ESG Risk | C28: =INDEX('DMA Matrix'!$H$5:$H$34,MATCH($A28,'DMA Matrix'!$A$5:$A$34,0)) -> Double Material | D28: ESG risks affecting business continuity, strategy and stakeholders | E28: Risk + Opportunity | F28: Integrate material ESG risks into enterprise risk management and strategic planning. | G28: ESG risks in ERM; mitigation closure rate | H28: Critical
A29: G05 | B29: Cybersecurity — Cyber Risk | C29: =INDEX('DMA Matrix'!$H$5:$H$34,MATCH($A29,'DMA Matrix'!$A$5:$A$34,0)) -> Double Material | D29: Cyber threats affecting critical infrastructure and operations | E29: Risk | F29: Strengthen IT/OT cybersecurity, incident response and resilience testing across critical assets. | G29: Cyber incidents; systems tested; response time | H29: Critical
... A34: G10 | B34: Creating Economic Value | C34: =INDEX('DMA Matrix'!$H$5:$H$34,MATCH($A34,'DMA Matrix'!$A$5:$A$34,0)) -> Double Material | D34: Responsible economic contribution, tax compliance and stakeholder value creation | E34: Risk + Opportunity | F34: Strengthen tax governance, compliance controls and transparent economic-value reporting. | G34: Tax compliance incidents; economic value distributed | H34: High

Sheet Benchmark
A1: Tata Power - Benchmark | FY2025–26
A2: Tata Powers Offcicial DMA vs Independent DMA
A3: Official = Integrated Annual Report 2025-26 pp.78-81 (27 topics; bands READ FROM THE MATRIX CHART, approximate near band edges). Project = DMA Matrix scores (live link to the DMA Matrix sheet, by topic ID). Mapping, band cut-offs and grade thresholds are analyst-defined; see notes below.
B6: Topics in Independent DMA | C6: =COUNTA($A$33:$A$62) -> 30
B7: Official topics (FY26) | C7: 27
B8: Official 'Very High priority' topics | C8: 10
B9: Official 'High priority' topics (read from chart) | C9: 14
B10: Official 'Medium priority' topics | C10: =C7-C8-C9 -> 3
B11: Cut-off rank for Very High-equivalent (project topics) | C11: =ROUND(C6*C8/C7,0) -> 11
B12: Cut-off rank for High-equivalent (project topics) | C12: =ROUND(C6*(C8+C9)/C7,0) -> 27
B13: Absolute Tier 1 cut-off (impact AND financial >=) | C13: 4
B14: Absolute Tier 2 cut-off (impact AND financial >=) | C14: 3.5
B15: Grade A needs: Alignment Index >= | C15: 0.8
B16: Grade A needs: top-band Recall >= | C16: 0.7
B17: Grade B needs: Alignment Index >= | C17: 0.65
B18: Grade B needs: top-band Recall >= | C18: 0.5
B20: RESULTS
B21: Alignment Index (avg alignment score / 3) | C21: =SUMIFS($P$33:$P$62,$N$33:$N$62,"Y")/(3*COUNTIF($N$33:$N$62,"Y")) -> 0.84615385
B22: Top-band Recall (official Very High that you also rank Very High-equivalent) | C22: =COUNTIFS($N$33:$N$62,"Y",$G$33:$G$62,"Very High",$K$33:$K$62,"Very High")/C8 -> 0.6
B23: Top-band Precision (your Very High-equivalent that official also rates Very High) | C23: =COUNTIFS($N$33:$N$62,"Y",$G$33:$G$62,"Very High",$K$33:$K$62,"Very High")/COUNTIFS($N$33:$N$62,"Y",$G$33:$G$62,"Very High") -> 0.6
B24: Overall benchmark grade | C24: =IF(AND(C21>=C15,C22>=C16),"A: Strong",IF(AND(C21>=C17,C22>=C18),"B: Moderate","C: Weak")) -> B: Moderate
B25: Topics aligned exactly | C25: =COUNTIFS($Q$33:$Q$62,"Aligned",$N$33:$N$62,"Y") -> 14
B26: Topics you rate higher than official | C26: =COUNTIFS($Q$33:$Q$62,"You rate higher",$N$33:$N$62,"Y") -> 7
B27: Topics official rates higher than you | C27: =COUNTIFS($Q$33:$Q$62,"Official rates higher",$N$33:$N$62,"Y") -> 5
B28: Topics with no official equivalent / missing from your universe | C28: =COUNTIF($Q$33:$Q$62,"No official equivalent")+COUNTIF($Q$33:$Q$62,"Missing from your universe") -> 2
B29: Edge cases (rank within 1 of a band cut-off): treat with care | C29: =COUNTIF($R$33:$R$62,"Edge") -> 3
B30: Read-across | C30: =IF(C24="A: Strong","Broadly consistent with the official view",IF(C24="B: Moderate","Consistent overall, but your top tier misses part of the official Very High set","Materially different from the official view")) -> Consistent overall, but your top tier misses part of the official Very High set
A32: Your ID | B32: Project topic | C32: Project impact score | D32: Project financial score | E32: Priority score (impact x financial) | F32: Rank (1 = highest) | G32: Project band (distribution-matched) | H32: Project tier (absolute cut-offs) | I32: Official # | J32: Official topic (FY26) | K32: Official band | L32: Official band certainty | M32: Mapping | N32: Counts in index? | O32: Gap (Project - Official) | P32: Alignment score (0-3) | Q32: Status | R32: Edge case? | S32: Recommended action | T32: What to say / next check
A33: E01 | B33: =INDEX('DMA Matrix'!$C$5:$C$34,MATCH($A33,'DMA Matrix'!$A$5:$A$34,0)) -> Climate Change | C33: =INDEX('DMA Matrix'!$D$5:$D$34,MATCH($A33,'DMA Matrix'!$A$5:$A$34,0)) -> 5 | D33: =INDEX('DMA Matrix'!$F$5:$F$34,MATCH($A33,'DMA Matrix'!$A$5:$A$34,0)) -> 5 | E33: =C33*D33 -> 25 | F33: =RANK(E33,$E$33:$E$62,0) -> 1 | G33: =IF(F33<=$C$11,"Very High",IF(F33<=$C$12,"High","Medium")) -> Very High | H33: =IF(AND(C33>=$C$13,D33>=$C$13),"Tier 1",IF(AND(C33>=$C$14,D33>=$C$14),"Tier 2","Tier 3")) -> Tier 1 | I33: 1 | J33: Climate strategy | K33: Very High | L33: High | M33: One-to-one | N33: Y | O33: =IF(K33="n/a","",IF(G33="Very High",3,IF(G33="High",2,1))-IF(K33="Very High",3,IF(K33="High",2,1))) -> 0 | P33: =IF(OR(N33="N",O33=""),"",3-ABS(O33)) -> 3 | Q33: =IF(B33="","Missing from your universe",IF(K33="n/a","No official equivalent",IF(O33=0,"Aligned",IF(O33>0,"You rate higher","Official rates higher")))) -> Aligned | R33: =IF(OR(ABS(F33-$C$11)<=1,ABS(F33-$C$12)<=1),"Edge","") | S33: =IF(Q33="Aligned","Keep",IF(Q33="You rate higher","Justify or lower",IF(Q33="Official rates higher","Re-check scoring / raise",IF(Q33="No official equivalent","Keep as sector add-on; justify","Add or map to existing topic")))) -> Keep | T33: Both top band.
A34: E02 | B34: =INDEX('DMA Matrix'!$C$5:$C$34,MATCH($A34,'DMA Matrix'!$A$5:$A$34,0)) -> GHG Emissions | C34: =INDEX('DMA Matrix'!$D$5:$D$34,MATCH($A34,'DMA Matrix'!$A$5:$A$34,0)) -> 5 | D34: =INDEX('DMA Matrix'!$F$5:$F$34,MATCH($A34,'DMA Matrix'!$A$5:$A$34,0)) -> 5 | E34: =C34*D34 -> 25 | F34: =RANK(E34,$E$33:$E$62,0) -> 1 | G34: =IF(F34<=$C$11,"Very High",IF(F34<=$C$12,"High","Medium")) -> Very High | H34: =IF(AND(C34>=$C$13,D34>=$C$13),"Tier 1",IF(AND(C34>=$C$14,D34>=$C$14),"Tier 2","Tier 3")) -> Tier 1 | I34: 2 | J34: Emissions management | K34: Very High | L34: High | M34: Merged | N34: Y | O34: =IF(K34="n/a","",IF(G34="Very High",3,IF(G34="High",2,1))-IF(K34="Very High",3,IF(K34="High",2,1))) -> 0 | P34: =IF(OR(N34="N",O34=""),"",3-ABS(O34)) -> 3 | Q34: =IF(B34="","Missing from your universe",IF(K34="n/a","No official equivalent",IF(O34=0,"Aligned",IF(O34>0,"You rate higher","Official rates higher")))) -> Aligned | R34: =IF(OR(ABS(F34-$C$11)<=1,ABS(F34-$C$12)<=1),"Edge","") | S34: =IF(Q34="Aligned","Keep",IF(Q34="You rate higher","Justify or lower",IF(Q34="Official rates higher","Re-check scoring / raise",IF(Q34="No official equivalent","Keep as sector add-on; justify","Add or map to existing topic")))) -> Keep | T34: Official #2 covers GHG plus SOx/NOx/PM together (BRSR p.293).
A35: E03 | B35: =INDEX('DMA Matrix'!$C$5:$C$34,MATCH($A35,'DMA Matrix'!$A$5:$A$34,0)) -> Energy Management | C35: =INDEX('DMA Matrix'!$D$5:$D$34,MATCH($A35,'DMA Matrix'!$A$5:$A$34,0)) -> 3.3333333 | D35: =INDEX('DMA Matrix'!$F$5:$F$34,MATCH($A35,'DMA Matrix'!$A$5:$A$34,0)) -> 4 | E35: =C35*D35 -> 13.333333 | F35: =RANK(E35,$E$33:$E$62,0) -> 16 | G35: =IF(F35<=$C$11,"Very High",IF(F35<=$C$12,"High","Medium")) -> High | H35: =IF(AND(C35>=$C$13,D35>=$C$13),"Tier 1",IF(AND(C35>=$C$14,D35>=$C$14),"Tier 2","Tier 3")) -> Tier 3 | I35: 3 | J35: Energy management | K35: Very High | L35: High | M35: 1:1 | N35: Y | O35: =IF(K35="n/a","",IF(G35="Very High",3,IF(G35="High",2,1))-IF(K35="Very High",3,IF(K35="High",2,1))) -> -1 | P35: =IF(OR(N35="N",O35=""),"",3-ABS(O35)) -> 2 | Q35: =IF(B35="","Missing from your universe",IF(K35="n/a","No official equivalent",IF(O35=0,"Aligned",IF(O35>0,"You rate higher","Official rates higher")))) -> Official rates higher | R35: =IF(OR(ABS(F35-$C$11)<=1,ABS(F35-$C$12)<=1),"Edge","") | S35: =IF(Q35="Aligned","Keep",IF(Q35="You rate higher","Justify or lower",IF(Q35="Official rates higher","Re-check scoring / raise",IF(Q35="No official equivalent","Keep as sector add-on; justify","Add or map to existing topic")))) -> Re-check scoring / raise | T35: =IF(Q35="Official rates higher","Official Very High. Your impact score ("&TEXT(C35,"0.00")&") held it down: re-check the impact rationale (auxiliary power, distribution losses).","Aligned with the official band on your current scores (impact "&TEXT(C35,"0.00")&").") -> Official Very High. Your impact score (3.33) held it down: re-check the impact rationale (auxiliary power, distribution losses).
A36: E04 | B36: =INDEX('DMA Matrix'!$C$5:$C$34,MATCH($A36,'DMA Matrix'!$A$5:$A$34,0)) -> Air Pollution | C36: =INDEX('DMA Matrix'!$D$5:$D$34,MATCH($A36,'DMA Matrix'!$A$5:$A$34,0)) -> 4.1166667 | D36: =INDEX('DMA Matrix'!$F$5:$F$34,MATCH($A36,'DMA Matrix'!$A$5:$A$34,0)) -> 3.8 | E36: =C36*D36 -> 15.643333 | F36: =RANK(E36,$E$33:$E$62,0) -> 10 | G36: =IF(F36<=$C$11,"Very High",IF(F36<=$C$12,"High","Medium")) -> Very High | H36: =IF(AND(C36>=$C$13,D36>=$C$13),"Tier 1",IF(AND(C36>=$C$14,D36>=$C$14),"Tier 2","Tier 3")) -> Tier 2 | I36: 2 | J36: Emissions management | K36: Very High | L36: High | M36: Merged | N36: N | O36: =IF(K36="n/a","",IF(G36="Very High",3,IF(G36="High",2,1))-IF(K36="Very High",3,IF(K36="High",2,1))) -> 0 | P36: =IF(OR(N36="N",O36=""),"",3-ABS(O36)) | Q36: =IF(B36="","Missing from your universe",IF(K36="n/a","No official equivalent",IF(O36=0,"Aligned",IF(O36>0,"You rate higher","Official rates higher")))) -> Aligned | R36: =IF(OR(ABS(F36-$C$11)<=1,ABS(F36-$C$12)<=1),"Edge","") -> Edge | S36: =IF(Q36="Aligned","Keep",IF(Q36="You rate higher","Justify or lower",IF(Q36="Official rates higher","Re-check scoring / raise",IF(Q36="No official equivalent","Keep as sector add-on; justify","Add or map to existing topic")))) -> Keep | T36: Folded into official #2, so excluded from the index to avoid double counting.
A37: E05 | B37: =INDEX('DMA Matrix'!$C$5:$C$34,MATCH($A37,'DMA Matrix'!$A$5:$A$34,0)) -> Water & Effluent | C37: =INDEX('DMA Matrix'!$D$5:$D$34,MATCH($A37,'DMA Matrix'!$A$5:$A$34,0)) -> 3.8 | D37: =INDEX('DMA Matrix'!$F$5:$F$34,MATCH($A37,'DMA Matrix'!$A$5:$A$34,0)) -> 3.8 | E37: =C37*D37 -> 14.44 | F37: =RANK(E37,$E$33:$E$62,0) -> 13 | G37: =IF(F37<=$C$11,"Very High",IF(F37<=$C$12,"High","Medium")) -> High | H37: =IF(AND(C37>=$C$13,D37>=$C$13),"Tier 1",IF(AND(C37>=$C$14,D37>=$C$14),"Tier 2","Tier 3")) -> Tier 2 | I37: 7 | J37: Water and effluent management | K37: Very High | L37: High | M37: 1:1 | N37: Y | O37: =IF(K37="n/a","",IF(G37="Very High",3,IF(G37="High",2,1))-IF(K37="Very High",3,IF(K37="High",2,1))) -> -1 | P37: =IF(OR(N37="N",O37=""),"",3-ABS(O37)) -> 2 | Q37: =IF(B37="","Missing from your universe",IF(K37="n/a","No official equivalent",IF(O37=0,"Aligned",IF(O37>0,"You rate higher","Official rates higher")))) -> Official rates higher | R37: =IF(OR(ABS(F37-$C$11)<=1,ABS(F37-$C$12)<=1),"Edge","") | S37: =IF(Q37="Aligned","Keep",IF(Q37="You rate higher","Justify or lower",IF(Q37="Official rates higher","Re-check scoring / raise",IF(Q37="No official equivalent","Keep as sector add-on; justify","Add or map to existing topic")))) -> Re-check scoring / raise | T37: Official Very High. Company has a 2030 water-neutrality goal and 'Aspiring' certification (BRSR p.319). Best re-tier candidate.
A38: E06 | B38: =INDEX('DMA Matrix'!$C$5:$C$34,MATCH($A38,'DMA Matrix'!$A$5:$A$34,0)) -> Biodiversity | C38: =INDEX('DMA Matrix'!$D$5:$D$34,MATCH($A38,'DMA Matrix'!$A$5:$A$34,0)) -> 3.6833333 | D38: =INDEX('DMA Matrix'!$F$5:$F$34,MATCH($A38,'DMA Matrix'!$A$5:$A$34,0)) -> 2.55 | E38: =C38*D38 -> 9.3925 | F38: =RANK(E38,$E$33:$E$62,0) -> 24 | G38: =IF(F38<=$C$11,"Very High",IF(F38<=$C$12,"High","Medium")) -> High | H38: =IF(AND(C38>=$C$13,D38>=$C$13),"Tier 1",IF(AND(C38>=$C$14,D38>=$C$14),"Tier 2","Tier 3")) -> Tier 3 | I38: 5 | J38: Safeguarding biodiversity | K38: High | L38: High | M38: 1:1 | N38: Y | O38: =IF(K38="n/a","",IF(G38="Very High",3,IF(G38="High",2,1))-IF(K38="Very High",3,IF(K38="High",2,1))) -> 0 | P38: =IF(OR(N38="N",O38=""),"",3-ABS(O38)) -> 3 | Q38: =IF(B38="","Missing from your universe",IF(K38="n/a","No official equivalent",IF(O38=0,"Aligned",IF(O38>0,"You rate higher","Official rates higher")))) -> Aligned | R38: =IF(OR(ABS(F38-$C$11)<=1,ABS(F38-$C$12)<=1),"Edge","") | S38: =IF(Q38="Aligned","Keep",IF(Q38="You rate higher","Justify or lower",IF(Q38="Official rates higher","Re-check scoring / raise",IF(Q38="No official equivalent","Keep as sector add-on; justify","Add or map to existing topic")))) -> Keep | T38: Both see high impact, lower financial (official dot sits high on the impact axis).
A39: E07 | B39: =INDEX('DMA Matrix'!$C$5:$C$34,MATCH($A39,'DMA Matrix'!$A$5:$A$34,0)) -> Waste Management | C39: =INDEX('DMA Matrix'!$D$5:$D$34,MATCH($A39,'DMA Matrix'!$A$5:$A$34,0)) -> 3.1666667 | D39: =INDEX('DMA Matrix'!$F$5:$F$34,MATCH($A39,'DMA Matrix'!$A$5:$A$34,0)) -> 2.85 | E39: =C39*D39 -> 9.025 | F39: =RANK(E39,$E$33:$E$62,0) -> 25 | G39: =IF(F39<=$C$11,"Very High",IF(F39<=$C$12,"High","Medium")) -> High | H39: =IF(AND(C39>=$C$13,D39>=$C$13),"Tier 1",IF(AND(C39>=$C$14,D39>=$C$14),"Tier 2","Tier 3")) -> Tier 3 | I39: 6 | J39: Hazardous and toxic waste management | K39: High | L39: High | M39: Reframed | N39: Y | O39: =IF(K39="n/a","",IF(G39="Very High",3,IF(G39="High",2,1))-IF(K39="Very High",3,IF(K39="High",2,1))) -> 0 | P39: =IF(OR(N39="N",O39=""),"",3-ABS(O39)) -> 3 | Q39: =IF(B39="","Missing from your universe",IF(K39="n/a","No official equivalent",IF(O39=0,"Aligned",IF(O39>0,"You rate higher","Official rates higher")))) -> Aligned | R39: =IF(OR(ABS(F39-$C$11)<=1,ABS(F39-$C$12)<=1),"Edge","") | S39: =IF(Q39="Aligned","Keep",IF(Q39="You rate higher","Justify or lower",IF(Q39="Official rates higher","Re-check scoring / raise",IF(Q39="No official equivalent","Keep as sector add-on; justify","Add or map to existing topic")))) -> Keep | T39: Official topic is narrower (hazardous & toxic); yours also spans non-hazardous waste.
A40: E08 | B40: =INDEX('DMA Matrix'!$C$5:$C$34,MATCH($A40,'DMA Matrix'!$A$5:$A$34,0)) -> Ash Management | C40: =INDEX('DMA Matrix'!$D$5:$D$34,MATCH($A40,'DMA Matrix'!$A$5:$A$34,0)) -> 3.4833333 | D40: =INDEX('DMA Matrix'!$F$5:$F$34,MATCH($A40,'DMA Matrix'!$A$5:$A$34,0)) -> 3.8 | E40: =C40*D40 -> 13.236667 | F40: =RANK(E40,$E$33:$E$62,0) -> 17 | G40: =IF(F40<=$C$11,"Very High",IF(F40<=$C$12,"High","Medium")) -> High | H40: =IF(AND(C40>=$C$13,D40>=$C$13),"Tier 1",IF(AND(C40>=$C$14,D40>=$C$14),"Tier 2","Tier 3")) -> Tier 3 | I40: n/a | J40: No standalone official topic | K40: n/a | L40: n/a | M40: None | N40: N | O40: =IF(K40="n/a","",IF(G40="Very High",3,IF(G40="High",2,1))-IF(K40="Very High",3,IF(K40="High",2,1))) | P40: =IF(OR(N40="N",O40=""),"",3-ABS(O40)) | Q40: =IF(B40="","Missing from your universe",IF(K40="n/a","No official equivalent",IF(O40=0,"Aligned",IF(O40>0,"You rate higher","Official rates higher")))) -> No official equivalent | R40: =IF(OR(ABS(F40-$C$11)<=1,ABS(F40-$C$12)<=1),"Edge","") | S40: =IF(Q40="Aligned","Keep",IF(Q40="You rate higher","Justify or lower",IF(Q40="Official rates higher","Re-check scoring / raise",IF(Q40="No official equivalent","Keep as sector add-on; justify","Add or map to existing topic")))) -> Keep as sector add-on; justify | T40: Sector-specific addition by you; no ash topic in the official list. Keep and say why.
A41: E09 | B41: =INDEX('DMA Matrix'!$C$5:$C$34,MATCH($A41,'DMA Matrix'!$A$5:$A$34,0)) -> Land Use | C41: =INDEX('DMA Matrix'!$D$5:$D$34,MATCH($A41,'DMA Matrix'!$A$5:$A$34,0)) -> 3.1166667 | D41: =INDEX('DMA Matrix'!$F$5:$F$34,MATCH($A41,'DMA Matrix'!$A$5:$A$34,0)) -> 2.55 | E41: =C41*D41 -> 7.9475 | F41: =RANK(E41,$E$33:$E$62,0) -> 29 | G41: =IF(F41<=$C$11,"Very High",IF(F41<=$C$12,"High","Medium")) -> Medium | H41: =IF(AND(C41>=$C$13,D41>=$C$13),"Tier 1",IF(AND(C41>=$C$14,D41>=$C$14),"Tier 2","Tier 3")) -> Tier 3 | I41: n/a | J41: No standalone official topic | K41: n/a | L41: n/a | M41: None | N41: N | O41: =IF(K41="n/a","",IF(G41="Very High",3,IF(G41="High",2,1))-IF(K41="Very High",3,IF(K41="High",2,1))) | P41: =IF(OR(N41="N",O41=""),"",3-ABS(O41)) | Q41: =IF(B41="","Missing from your universe",IF(K41="n/a","No official equivalent",IF(O41=0,"Aligned",IF(O41>0,"You rate higher","Official rates higher")))) -> No official equivalent | R41: =IF(OR(ABS(F41-$C$11)<=1,ABS(F41-$C$12)<=1),"Edge","") | S41: =IF(Q41="Aligned","Keep",IF(Q41="You rate higher","Justify or lower",IF(Q41="Official rates higher","Re-check scoring / raise",IF(Q41="No official equivalent","Keep as sector add-on; justify","Add or map to existing topic")))) -> Keep as sector add-on; justify | T41: Land footprint appears only as a negative impact under official #4 (BRSR p.294).
A42: E10 | B42: =INDEX('DMA Matrix'!$C$5:$C$34,MATCH($A42,'DMA Matrix'!$A$5:$A$34,0)) -> Resource Use & Circular Economy | C42: =INDEX('DMA Matrix'!$D$5:$D$34,MATCH($A42,'DMA Matrix'!$A$5:$A$34,0)) -> 3.1666667 | D42: =INDEX('DMA Matrix'!$F$5:$F$34,MATCH($A42,'DMA Matrix'!$A$5:$A$34,0)) -> 2.85 | E42: =C42*D42 -> 9.025 | F42: =RANK(E42,$E$33:$E$62,0) -> 25 | G42: =IF(F42<=$C$11,"Very High",IF(F42<=$C$12,"High","Medium")) -> High | H42: =IF(AND(C42>=$C$13,D42>=$C$13),"Tier 1",IF(AND(C42>=$C$14,D42>=$C$14),"Tier 2","Tier 3")) -> Tier 3 | I42: 8 | J42: Product design and lifecycle management* | K42: Medium | L42: High | M42: Reframed | N42: Y | O42: =IF(K42="n/a","",IF(G42="Very High",3,IF(G42="High",2,1))-IF(K42="Very High",3,IF(K42="High",2,1))) -> 1 | P42: =IF(OR(N42="N",O42=""),"",3-ABS(O42)) -> 2 | Q42: =IF(B42="","Missing from your universe",IF(K42="n/a","No official equivalent",IF(O42=0,"Aligned",IF(O42>0,"You rate higher","Official rates higher")))) -> You rate higher | R42: =IF(OR(ABS(F42-$C$11)<=1,ABS(F42-$C$12)<=1),"Edge","") | S42: =IF(Q42="Aligned","Keep",IF(Q42="You rate higher","Justify or lower",IF(Q42="Official rates higher","Re-check scoring / raise",IF(Q42="No official equivalent","Keep as sector add-on; justify","Add or map to existing topic")))) -> Justify or lower | T42: New in FY26 and only Medium. Broader than your circularity framing; check whether PV/battery end-of-life sits here.
A43: S01 | B43: =INDEX('DMA Matrix'!$C$5:$C$34,MATCH($A43,'DMA Matrix'!$A$5:$A$34,0)) -> Occupational Health & Safety | C43: =INDEX('DMA Matrix'!$D$5:$D$34,MATCH($A43,'DMA Matrix'!$A$5:$A$34,0)) -> 4.4333333 | D43: =INDEX('DMA Matrix'!$F$5:$F$34,MATCH($A43,'DMA Matrix'!$A$5:$A$34,0)) -> 4.75 | E43: =C43*D43 -> 21.058333 | F43: =RANK(E43,$E$33:$E$62,0) -> 5 | G43: =IF(F43<=$C$11,"Very High",IF(F43<=$C$12,"High","Medium")) -> Very High | H43: =IF(AND(C43>=$C$13,D43>=$C$13),"Tier 1",IF(AND(C43>=$C$14,D43>=$C$14),"Tier 2","Tier 3")) -> Tier 1 | I43: 13 | J43: Occupational health and safety | K43: Very High | L43: High | M43: 1:1 | N43: Y | O43: =IF(K43="n/a","",IF(G43="Very High",3,IF(G43="High",2,1))-IF(K43="Very High",3,IF(K43="High",2,1))) -> 0 | P43: =IF(OR(N43="N",O43=""),"",3-ABS(O43)) -> 3 | Q43: =IF(B43="","Missing from your universe",IF(K43="n/a","No official equivalent",IF(O43=0,"Aligned",IF(O43>0,"You rate higher","Official rates higher")))) -> Aligned | R43: =IF(OR(ABS(F43-$C$11)<=1,ABS(F43-$C$12)<=1),"Edge","") | S43: =IF(Q43="Aligned","Keep",IF(Q43="You rate higher","Justify or lower",IF(Q43="Official rates higher","Re-check scoring / raise",IF(Q43="No official equivalent","Keep as sector add-on; justify","Add or map to existing topic")))) -> Keep | T43: Both top band; official dot 13 is highest on impact.
A44: S02 | B44: =INDEX('DMA Matrix'!$C$5:$C$34,MATCH($A44,'DMA Matrix'!$A$5:$A$34,0)) -> Employee Health, Wellbeing & Engagement | C44: =INDEX('DMA Matrix'!$D$5:$D$34,MATCH($A44,'DMA Matrix'!$A$5:$A$34,0)) -> 3.1666667 | D44: =INDEX('DMA Matrix'!$F$5:$F$34,MATCH($A44,'DMA Matrix'!$A$5:$A$34,0)) -> 2.85 | E44: =C44*D44 -> 9.025 | F44: =RANK(E44,$E$33:$E$62,0) -> 25 | G44: =IF(F44<=$C$11,"Very High",IF(F44<=$C$12,"High","Medium")) -> High | H44: =IF(AND(C44>=$C$13,D44>=$C$13),"Tier 1",IF(AND(C44>=$C$14,D44>=$C$14),"Tier 2","Tier 3")) -> Tier 3 | I44: 11 | J44: Responsible employer | K44: Medium | L44: High | M44: Reframed | N44: Y | O44: =IF(K44="n/a","",IF(G44="Very High",3,IF(G44="High",2,1))-IF(K44="Very High",3,IF(K44="High",2,1))) -> 1 | P44: =IF(OR(N44="N",O44=""),"",3-ABS(O44)) -> 2 | Q44: =IF(B44="","Missing from your universe",IF(K44="n/a","No official equivalent",IF(O44=0,"Aligned",IF(O44>0,"You rate higher","Official rates higher")))) -> You rate higher | R44: =IF(OR(ABS(F44-$C$11)<=1,ABS(F44-$C$12)<=1),"Edge","") | S44: =IF(Q44="Aligned","Keep",IF(Q44="You rate higher","Justify or lower",IF(Q44="Official rates higher","Re-check scoring / raise",IF(Q44="No official equivalent","Keep as sector add-on; justify","Add or map to existing topic")))) -> Justify or lower | T44: Renamed in FY26 from 'Socially responsible employer' (AR p.79).
A45: S03 | B45: =INDEX('DMA Matrix'!$C$5:$C$34,MATCH($A45,'DMA Matrix'!$A$5:$A$34,0)) -> Diversity & Inclusion | C45: =INDEX('DMA Matrix'!$D$5:$D$34,MATCH($A45,'DMA Matrix'!$A$5:$A$34,0)) -> 3.1666667 | D45: =INDEX('DMA Matrix'!$F$5:$F$34,MATCH($A45,'DMA Matrix'!$A$5:$A$34,0)) -> 2.85 | E45: =C45*D45 -> 9.025 | F45: =RANK(E45,$E$33:$E$62,0) -> 25 | G45: =IF(F45<=$C$11,"Very High",IF(F45<=$C$12,"High","Medium")) -> High | H45: =IF(AND(C45>=$C$13,D45>=$C$13),"Tier 1",IF(AND(C45>=$C$14,D45>=$C$14),"Tier 2","Tier 3")) -> Tier 3 | I45: 10 | J45: Diversity and inclusion in workplace | K45: Medium | L45: High | M45: 1:1 | N45: Y | O45: =IF(K45="n/a","",IF(G45="Very High",3,IF(G45="High",2,1))-IF(K45="Very High",3,IF(K45="High",2,1))) -> 1 | P45: =IF(OR(N45="N",O45=""),"",3-ABS(O45)) -> 2 | Q45: =IF(B45="","Missing from your universe",IF(K45="n/a","No official equivalent",IF(O45=0,"Aligned",IF(O45>0,"You rate higher","Official rates higher")))) -> You rate higher | R45: =IF(OR(ABS(F45-$C$11)<=1,ABS(F45-$C$12)<=1),"Edge","") | S45: =IF(Q45="Aligned","Keep",IF(Q45="You rate higher","Justify or lower",IF(Q45="Official rates higher","Re-check scoring / raise",IF(Q45="No official equivalent","Keep as sector add-on; justify","Add or map to existing topic")))) -> Justify or lower | T45: Official has it Medium; you rank it near the bottom too (tie), so the gap is a band-edge effect.
A46: S04 | B46: =INDEX('DMA Matrix'!$C$5:$C$34,MATCH($A46,'DMA Matrix'!$A$5:$A$34,0)) -> Talent Development | C46: =INDEX('DMA Matrix'!$D$5:$D$34,MATCH($A46,'DMA Matrix'!$A$5:$A$34,0)) -> 2.85 | D46: =INDEX('DMA Matrix'!$F$5:$F$34,MATCH($A46,'DMA Matrix'!$A$5:$A$34,0)) -> 3.8 | E46: =C46*D46 -> 10.83 | F46: =RANK(E46,$E$33:$E$62,0) -> 22 | G46: =IF(F46<=$C$11,"Very High",IF(F46<=$C$12,"High","Medium")) -> High | H46: =IF(AND(C46>=$C$13,D46>=$C$13),"Tier 1",IF(AND(C46>=$C$14,D46>=$C$14),"Tier 2","Tier 3")) -> Tier 3 | I46: 12 | J46: Employee retention, engagement and talent development | K46: High | L46: High | M46: 1:1 | N46: Y | O46: =IF(K46="n/a","",IF(G46="Very High",3,IF(G46="High",2,1))-IF(K46="Very High",3,IF(K46="High",2,1))) -> 0 | P46: =IF(OR(N46="N",O46=""),"",3-ABS(O46)) -> 3 | Q46: =IF(B46="","Missing from your universe",IF(K46="n/a","No official equivalent",IF(O46=0,"Aligned",IF(O46>0,"You rate higher","Official rates higher")))) -> Aligned | R46: =IF(OR(ABS(F46-$C$11)<=1,ABS(F46-$C$12)<=1),"Edge","") | S46: =IF(Q46="Aligned","Keep",IF(Q46="You rate higher","Justify or lower",IF(Q46="Official rates higher","Re-check scoring / raise",IF(Q46="No official equivalent","Keep as sector add-on; justify","Add or map to existing topic")))) -> Keep | T46: =IF(C46<3,"Dashboard headline replaced: the 'only financially-material topic' claim rested on a "&TEXT(3-C46,"0.00")&" gap to the 3.00 threshold.","Now Double Material on your scores; no longer a special case.") -> Dashboard headline replaced: the 'only financially-material topic' claim rested on a 0.15 gap to the 3.00 threshold.
A47: S05 | B47: =INDEX('DMA Matrix'!$C$5:$C$34,MATCH($A47,'DMA Matrix'!$A$5:$A$34,0)) -> Labour Relations & Working Conditions | C47: =INDEX('DMA Matrix'!$D$5:$D$34,MATCH($A47,'DMA Matrix'!$A$5:$A$34,0)) -> 3.4 | D47: =INDEX('DMA Matrix'!$F$5:$F$34,MATCH($A47,'DMA Matrix'!$A$5:$A$34,0)) -> 3.4 | E47: =C47*D47 -> 11.56 | F47: =RANK(E47,$E$33:$E$62,0) -> 20 | G47: =IF(F47<=$C$11,"Very High",IF(F47<=$C$12,"High","Medium")) -> High | H47: =IF(AND(C47>=$C$13,D47>=$C$13),"Tier 1",IF(AND(C47>=$C$14,D47>=$C$14),"Tier 2","Tier 3")) -> Tier 3 | I47: 14 | J47: Labour management | K47: High | L47: High | M47: 1:1 | N47: Y | O47: =IF(K47="n/a","",IF(G47="Very High",3,IF(G47="High",2,1))-IF(K47="Very High",3,IF(K47="High",2,1))) -> 0 | P47: =IF(OR(N47="N",O47=""),"",3-ABS(O47)) -> 3 | Q47: =IF(B47="","Missing from your universe",IF(K47="n/a","No official equivalent",IF(O47=0,"Aligned",IF(O47>0,"You rate higher","Official rates higher")))) -> Aligned | R47: =IF(OR(ABS(F47-$C$11)<=1,ABS(F47-$C$12)<=1),"Edge","") | S47: =IF(Q47="Aligned","Keep",IF(Q47="You rate higher","Justify or lower",IF(Q47="Official rates higher","Re-check scoring / raise",IF(Q47="No official equivalent","Keep as sector add-on; justify","Add or map to existing topic")))) -> Keep
A48: S06 | B48: =INDEX('DMA Matrix'!$C$5:$C$34,MATCH($A48,'DMA Matrix'!$A$5:$A$34,0)) -> Human Rights | C48: =INDEX('DMA Matrix'!$D$5:$D$34,MATCH($A48,'DMA Matrix'!$A$5:$A$34,0)) -> 3.9666667 | D48: =INDEX('DMA Matrix'!$F$5:$F$34,MATCH($A48,'DMA Matrix'!$A$5:$A$34,0)) -> 3.4 | E48: =C48*D48 -> 13.486667 | F48: =RANK(E48,$E$33:$E$62,0) -> 15 | G48: =IF(F48<=$C$11,"Very High",IF(F48<=$C$12,"High","Medium")) -> High | H48: =IF(AND(C48>=$C$13,D48>=$C$13),"Tier 1",IF(AND(C48>=$C$14,D48>=$C$14),"Tier 2","Tier 3")) -> Tier 3 | I48: 15 | J48: Human rights | K48: High | L48: High | M48: 1:1 | N48: Y | O48: =IF(K48="n/a","",IF(G48="Very High",3,IF(G48="High",2,1))-IF(K48="Very High",3,IF(K48="High",2,1))) -> 0 | P48: =IF(OR(N48="N",O48=""),"",3-ABS(O48)) -> 3 | Q48: =IF(B48="","Missing from your universe",IF(K48="n/a","No official equivalent",IF(O48=0,"Aligned",IF(O48>0,"You rate higher","Official rates higher")))) -> Aligned | R48: =IF(OR(ABS(F48-$C$11)<=1,ABS(F48-$C$12)<=1),"Edge","") | S48: =IF(Q48="Aligned","Keep",IF(Q48="You rate higher","Justify or lower",IF(Q48="Official rates higher","Re-check scoring / raise",IF(Q48="No official equivalent","Keep as sector add-on; justify","Add or map to existing topic")))) -> Keep
A49: S07 | B49: =INDEX('DMA Matrix'!$C$5:$C$34,MATCH($A49,'DMA Matrix'!$A$5:$A$34,0)) -> Community Impact | C49: =INDEX('DMA Matrix'!$D$5:$D$34,MATCH($A49,'DMA Matrix'!$A$5:$A$34,0)) -> 4.1166667 | D49: =INDEX('DMA Matrix'!$F$5:$F$34,MATCH($A49,'DMA Matrix'!$A$5:$A$34,0)) -> 3.4 | E49: =C49*D49 -> 13.996667 | F49: =RANK(E49,$E$33:$E$62,0) -> 14 | G49: =IF(F49<=$C$11,"Very High",IF(F49<=$C$12,"High","Medium")) -> High | H49: =IF(AND(C49>=$C$13,D49>=$C$13),"Tier 1",IF(AND(C49>=$C$14,D49>=$C$14),"Tier 2","Tier 3")) -> Tier 3 | I49: 17 | J49: Building sustainable communities | K49: High | L49: High | M49: Reframed | N49: Y | O49: =IF(K49="n/a","",IF(G49="Very High",3,IF(G49="High",2,1))-IF(K49="Very High",3,IF(K49="High",2,1))) -> 0 | P49: =IF(OR(N49="N",O49=""),"",3-ABS(O49)) -> 3 | Q49: =IF(B49="","Missing from your universe",IF(K49="n/a","No official equivalent",IF(O49=0,"Aligned",IF(O49>0,"You rate higher","Official rates higher")))) -> Aligned | R49: =IF(OR(ABS(F49-$C$11)<=1,ABS(F49-$C$12)<=1),"Edge","") | S49: =IF(Q49="Aligned","Keep",IF(Q49="You rate higher","Justify or lower",IF(Q49="Official rates higher","Re-check scoring / raise",IF(Q49="No official equivalent","Keep as sector add-on; justify","Add or map to existing topic")))) -> Keep
A50: S08 | B50: =INDEX('DMA Matrix'!$C$5:$C$34,MATCH($A50,'DMA Matrix'!$A$5:$A$34,0)) -> Access & Affordability | C50: =INDEX('DMA Matrix'!$D$5:$D$34,MATCH($A50,'DMA Matrix'!$A$5:$A$34,0)) -> 4.1166667 | D50: =INDEX('DMA Matrix'!$F$5:$F$34,MATCH($A50,'DMA Matrix'!$A$5:$A$34,0)) -> 4.75 | E50: =C50*D50 -> 19.554167 | F50: =RANK(E50,$E$33:$E$62,0) -> 6 | G50: =IF(F50<=$C$11,"Very High",IF(F50<=$C$12,"High","Medium")) -> Very High | H50: =IF(AND(C50>=$C$13,D50>=$C$13),"Tier 1",IF(AND(C50>=$C$14,D50>=$C$14),"Tier 2","Tier 3")) -> Tier 1 | I50: 9 | J50: Access and affordability* | K50: High | L50: High | M50: 1:1 | N50: Y | O50: =IF(K50="n/a","",IF(G50="Very High",3,IF(G50="High",2,1))-IF(K50="Very High",3,IF(K50="High",2,1))) -> 1 | P50: =IF(OR(N50="N",O50=""),"",3-ABS(O50)) -> 2 | Q50: =IF(B50="","Missing from your universe",IF(K50="n/a","No official equivalent",IF(O50=0,"Aligned",IF(O50>0,"You rate higher","Official rates higher")))) -> You rate higher | R50: =IF(OR(ABS(F50-$C$11)<=1,ABS(F50-$C$12)<=1),"Edge","") | S50: =IF(Q50="Aligned","Keep",IF(Q50="You rate higher","Justify or lower",IF(Q50="Official rates higher","Re-check scoring / raise",IF(Q50="No official equivalent","Keep as sector add-on; justify","Add or map to existing topic")))) -> Justify or lower | T50: New in FY26; official High. You rank it top-band: defend with consumer reach (13.1M) or lower it.
A51: S09 | B51: =INDEX('DMA Matrix'!$C$5:$C$34,MATCH($A51,'DMA Matrix'!$A$5:$A$34,0)) -> Customer Service & Consumer Protection | C51: =INDEX('DMA Matrix'!$D$5:$D$34,MATCH($A51,'DMA Matrix'!$A$5:$A$34,0)) -> 3.4833333 | D51: =INDEX('DMA Matrix'!$F$5:$F$34,MATCH($A51,'DMA Matrix'!$A$5:$A$34,0)) -> 3.8 | E51: =C51*D51 -> 13.236667 | F51: =RANK(E51,$E$33:$E$62,0) -> 17 | G51: =IF(F51<=$C$11,"Very High",IF(F51<=$C$12,"High","Medium")) -> High | H51: =IF(AND(C51>=$C$13,D51>=$C$13),"Tier 1",IF(AND(C51>=$C$14,D51>=$C$14),"Tier 2","Tier 3")) -> Tier 3 | I51: 16 | J51: Customer relationship management | K51: High | L51: High | M51: 1:1 | N51: Y | O51: =IF(K51="n/a","",IF(G51="Very High",3,IF(G51="High",2,1))-IF(K51="Very High",3,IF(K51="High",2,1))) -> 0 | P51: =IF(OR(N51="N",O51=""),"",3-ABS(O51)) -> 3 | Q51: =IF(B51="","Missing from your universe",IF(K51="n/a","No official equivalent",IF(O51=0,"Aligned",IF(O51>0,"You rate higher","Official rates higher")))) -> Aligned | R51: =IF(OR(ABS(F51-$C$11)<=1,ABS(F51-$C$12)<=1),"Edge","") | S51: =IF(Q51="Aligned","Keep",IF(Q51="You rate higher","Justify or lower",IF(Q51="Official rates higher","Re-check scoring / raise",IF(Q51="No official equivalent","Keep as sector add-on; justify","Add or map to existing topic")))) -> Keep
A52: S10 | B52: =INDEX('DMA Matrix'!$C$5:$C$34,MATCH($A52,'DMA Matrix'!$A$5:$A$34,0)) -> Energy Reliability | C52: =INDEX('DMA Matrix'!$D$5:$D$34,MATCH($A52,'DMA Matrix'!$A$5:$A$34,0)) -> 4.4333333 | D52: =INDEX('DMA Matrix'!$F$5:$F$34,MATCH($A52,'DMA Matrix'!$A$5:$A$34,0)) -> 5 | E52: =C52*D52 -> 22.166667 | F52: =RANK(E52,$E$33:$E$62,0) -> 4 | G52: =IF(F52<=$C$11,"Very High",IF(F52<=$C$12,"High","Medium")) -> Very High | H52: =IF(AND(C52>=$C$13,D52>=$C$13),"Tier 1",IF(AND(C52>=$C$14,D52>=$C$14),"Tier 2","Tier 3")) -> Tier 1 | I52: 4 | J52: Continuous and affordable green power | K52: Very High | L52: High | M52: Reframed | N52: Y | O52: =IF(K52="n/a","",IF(G52="Very High",3,IF(G52="High",2,1))-IF(K52="Very High",3,IF(K52="High",2,1))) -> 0 | P52: =IF(OR(N52="N",O52=""),"",3-ABS(O52)) -> 3 | Q52: =IF(B52="","Missing from your universe",IF(K52="n/a","No official equivalent",IF(O52=0,"Aligned",IF(O52>0,"You rate higher","Official rates higher")))) -> Aligned | R52: =IF(OR(ABS(F52-$C$11)<=1,ABS(F52-$C$12)<=1),"Edge","") | S52: =IF(Q52="Aligned","Keep",IF(Q52="You rate higher","Justify or lower",IF(Q52="Official rates higher","Re-check scoring / raise",IF(Q52="No official equivalent","Keep as sector add-on; justify","Add or map to existing topic")))) -> Keep | T52: Closest match to official #4 (supply continuity + green + affordable).
A53: G01 | B53: =INDEX('DMA Matrix'!$C$5:$C$34,MATCH($A53,'DMA Matrix'!$A$5:$A$34,0)) -> Business Ethics — Anti-corruption | C53: =INDEX('DMA Matrix'!$D$5:$D$34,MATCH($A53,'DMA Matrix'!$A$5:$A$34,0)) -> 3.4 | D53: =INDEX('DMA Matrix'!$F$5:$F$34,MATCH($A53,'DMA Matrix'!$A$5:$A$34,0)) -> 4.25 | E53: =C53*D53 -> 14.45 | F53: =RANK(E53,$E$33:$E$62,0) -> 12 | G53: =IF(F53<=$C$11,"Very High",IF(F53<=$C$12,"High","Medium")) -> High | H53: =IF(AND(C53>=$C$13,D53>=$C$13),"Tier 1",IF(AND(C53>=$C$14,D53>=$C$14),"Tier 2","Tier 3")) -> Tier 3 | I53: 22 | J53: Ethical business conduct | K53: Very High | L53: High | M53: 1:1 | N53: Y | O53: =IF(K53="n/a","",IF(G53="Very High",3,IF(G53="High",2,1))-IF(K53="Very High",3,IF(K53="High",2,1))) -> -1 | P53: =IF(OR(N53="N",O53=""),"",3-ABS(O53)) -> 2 | Q53: =IF(B53="","Missing from your universe",IF(K53="n/a","No official equivalent",IF(O53=0,"Aligned",IF(O53>0,"You rate higher","Official rates higher")))) -> Official rates higher | R53: =IF(OR(ABS(F53-$C$11)<=1,ABS(F53-$C$12)<=1),"Edge","") -> Edge | S53: =IF(Q53="Aligned","Keep",IF(Q53="You rate higher","Justify or lower",IF(Q53="Official rates higher","Re-check scoring / raise",IF(Q53="No official equivalent","Keep as sector add-on; justify","Add or map to existing topic")))) -> Re-check scoring / raise | T53: Official Very High (Tata Code of Conduct, bidding/PPA conduct: BRSR p.295). Biggest governance gap. Edge case.
A54: G02 | B54: =INDEX('DMA Matrix'!$C$5:$C$34,MATCH($A54,'DMA Matrix'!$A$5:$A$34,0)) -> Regulatory Compliance | C54: =INDEX('DMA Matrix'!$D$5:$D$34,MATCH($A54,'DMA Matrix'!$A$5:$A$34,0)) -> 4.1166667 | D54: =INDEX('DMA Matrix'!$F$5:$F$34,MATCH($A54,'DMA Matrix'!$A$5:$A$34,0)) -> 4.75 | E54: =C54*D54 -> 19.554167 | F54: =RANK(E54,$E$33:$E$62,0) -> 6 | G54: =IF(F54<=$C$11,"Very High",IF(F54<=$C$12,"High","Medium")) -> Very High | H54: =IF(AND(C54>=$C$13,D54>=$C$13),"Tier 1",IF(AND(C54>=$C$14,D54>=$C$14),"Tier 2","Tier 3")) -> Tier 1 | I54: 25 | J54: Regulatory compliance and landscape | K54: High | L54: High | M54: 1:1 | N54: Y | O54: =IF(K54="n/a","",IF(G54="Very High",3,IF(G54="High",2,1))-IF(K54="Very High",3,IF(K54="High",2,1))) -> 1 | P54: =IF(OR(N54="N",O54=""),"",3-ABS(O54)) -> 2 | Q54: =IF(B54="","Missing from your universe",IF(K54="n/a","No official equivalent",IF(O54=0,"Aligned",IF(O54>0,"You rate higher","Official rates higher")))) -> You rate higher | R54: =IF(OR(ABS(F54-$C$11)<=1,ABS(F54-$C$12)<=1),"Edge","") | S54: =IF(Q54="Aligned","Keep",IF(Q54="You rate higher","Justify or lower",IF(Q54="Official rates higher","Re-check scoring / raise",IF(Q54="No official equivalent","Keep as sector add-on; justify","Add or map to existing topic")))) -> Justify or lower | T54: You rank it top band; official High. Justify or lower.
A55: G03 | B55: =INDEX('DMA Matrix'!$C$5:$C$34,MATCH($A55,'DMA Matrix'!$A$5:$A$34,0)) -> ESG Governance | C55: =INDEX('DMA Matrix'!$D$5:$D$34,MATCH($A55,'DMA Matrix'!$A$5:$A$34,0)) -> 4.1166667 | D55: =INDEX('DMA Matrix'!$F$5:$F$34,MATCH($A55,'DMA Matrix'!$A$5:$A$34,0)) -> 3.8 | E55: =C55*D55 -> 15.643333 | F55: =RANK(E55,$E$33:$E$62,0) -> 10 | G55: =IF(F55<=$C$11,"Very High",IF(F55<=$C$12,"High","Medium")) -> Very High | H55: =IF(AND(C55>=$C$13,D55>=$C$13),"Tier 1",IF(AND(C55>=$C$14,D55>=$C$14),"Tier 2","Tier 3")) -> Tier 2 | I55: 20 | J55: ESG governance | K55: Very High | L55: High | M55: 1:1 | N55: Y | O55: =IF(K55="n/a","",IF(G55="Very High",3,IF(G55="High",2,1))-IF(K55="Very High",3,IF(K55="High",2,1))) -> 0 | P55: =IF(OR(N55="N",O55=""),"",3-ABS(O55)) -> 3 | Q55: =IF(B55="","Missing from your universe",IF(K55="n/a","No official equivalent",IF(O55=0,"Aligned",IF(O55>0,"You rate higher","Official rates higher")))) -> Aligned | R55: =IF(OR(ABS(F55-$C$11)<=1,ABS(F55-$C$12)<=1),"Edge","") -> Edge | S55: =IF(Q55="Aligned","Keep",IF(Q55="You rate higher","Justify or lower",IF(Q55="Official rates higher","Re-check scoring / raise",IF(Q55="No official equivalent","Keep as sector add-on; justify","Add or map to existing topic")))) -> Keep
A56: G04 | B56: =INDEX('DMA Matrix'!$C$5:$C$34,MATCH($A56,'DMA Matrix'!$A$5:$A$34,0)) -> Risk Management — ESG Risk | C56: =INDEX('DMA Matrix'!$D$5:$D$34,MATCH($A56,'DMA Matrix'!$A$5:$A$34,0)) -> 4.1166667 | D56: =INDEX('DMA Matrix'!$F$5:$F$34,MATCH($A56,'DMA Matrix'!$A$5:$A$34,0)) -> 4.75 | E56: =C56*D56 -> 19.554167 | F56: =RANK(E56,$E$33:$E$62,0) -> 6 | G56: =IF(F56<=$C$11,"Very High",IF(F56<=$C$12,"High","Medium")) -> Very High | H56: =IF(AND(C56>=$C$13,D56>=$C$13),"Tier 1",IF(AND(C56>=$C$14,D56>=$C$14),"Tier 2","Tier 3")) -> Tier 1 | I56: 21 | J56: Risk management and BCDMP | K56: High | L56: Medium | M56: 1:1 | N56: Y | O56: =IF(K56="n/a","",IF(G56="Very High",3,IF(G56="High",2,1))-IF(K56="Very High",3,IF(K56="High",2,1))) -> 1 | P56: =IF(OR(N56="N",O56=""),"",3-ABS(O56)) -> 2 | Q56: =IF(B56="","Missing from your universe",IF(K56="n/a","No official equivalent",IF(O56=0,"Aligned",IF(O56>0,"You rate higher","Official rates higher")))) -> You rate higher | R56: =IF(OR(ABS(F56-$C$11)<=1,ABS(F56-$C$12)<=1),"Edge","") | S56: =IF(Q56="Aligned","Keep",IF(Q56="You rate higher","Justify or lower",IF(Q56="Official rates higher","Re-check scoring / raise",IF(Q56="No official equivalent","Keep as sector add-on; justify","Add or map to existing topic")))) -> Justify or lower | T56: Official dot 21 sits just below the Very High curve (certainty Medium).
A57: G05 | B57: =INDEX('DMA Matrix'!$C$5:$C$34,MATCH($A57,'DMA Matrix'!$A$5:$A$34,0)) -> Cybersecurity — Cyber Risk | C57: =INDEX('DMA Matrix'!$D$5:$D$34,MATCH($A57,'DMA Matrix'!$A$5:$A$34,0)) -> 4.75 | D57: =INDEX('DMA Matrix'!$F$5:$F$34,MATCH($A57,'DMA Matrix'!$A$5:$A$34,0)) -> 4.75 | E57: =C57*D57 -> 22.5625 | F57: =RANK(E57,$E$33:$E$62,0) -> 3 | G57: =IF(F57<=$C$11,"Very High",IF(F57<=$C$12,"High","Medium")) -> Very High | H57: =IF(AND(C57>=$C$13,D57>=$C$13),"Tier 1",IF(AND(C57>=$C$14,D57>=$C$14),"Tier 2","Tier 3")) -> Tier 1 | I57: 24 | J57: Digitalisation, data privacy and cyber security | K57: Very High | L57: High | M57: Merged | N57: Y | O57: =IF(K57="n/a","",IF(G57="Very High",3,IF(G57="High",2,1))-IF(K57="Very High",3,IF(K57="High",2,1))) -> 0 | P57: =IF(OR(N57="N",O57=""),"",3-ABS(O57)) -> 3 | Q57: =IF(B57="","Missing from your universe",IF(K57="n/a","No official equivalent",IF(O57=0,"Aligned",IF(O57>0,"You rate higher","Official rates higher")))) -> Aligned | R57: =IF(OR(ABS(F57-$C$11)<=1,ABS(F57-$C$12)<=1),"Edge","") | S57: =IF(Q57="Aligned","Keep",IF(Q57="You rate higher","Justify or lower",IF(Q57="Official rates higher","Re-check scoring / raise",IF(Q57="No official equivalent","Keep as sector add-on; justify","Add or map to existing topic")))) -> Keep | T57: Official merged data privacy into this topic in FY26 (AR p.79).
A58: G06 | B58: =INDEX('DMA Matrix'!$C$5:$C$34,MATCH($A58,'DMA Matrix'!$A$5:$A$34,0)) -> Data Privacy | C58: =INDEX('DMA Matrix'!$D$5:$D$34,MATCH($A58,'DMA Matrix'!$A$5:$A$34,0)) -> 3.6833333 | D58: =INDEX('DMA Matrix'!$F$5:$F$34,MATCH($A58,'DMA Matrix'!$A$5:$A$34,0)) -> 3.4 | E58: =C58*D58 -> 12.523333 | F58: =RANK(E58,$E$33:$E$62,0) -> 19 | G58: =IF(F58<=$C$11,"Very High",IF(F58<=$C$12,"High","Medium")) -> High | H58: =IF(AND(C58>=$C$13,D58>=$C$13),"Tier 1",IF(AND(C58>=$C$14,D58>=$C$14),"Tier 2","Tier 3")) -> Tier 3 | I58: 24 | J58: Digitalisation, data privacy and cyber security | K58: Very High | L58: High | M58: Merged | N58: N | O58: =IF(K58="n/a","",IF(G58="Very High",3,IF(G58="High",2,1))-IF(K58="Very High",3,IF(K58="High",2,1))) -> -1 | P58: =IF(OR(N58="N",O58=""),"",3-ABS(O58)) | Q58: =IF(B58="","Missing from your universe",IF(K58="n/a","No official equivalent",IF(O58=0,"Aligned",IF(O58>0,"You rate higher","Official rates higher")))) -> Official rates higher | R58: =IF(OR(ABS(F58-$C$11)<=1,ABS(F58-$C$12)<=1),"Edge","") | S58: =IF(Q58="Aligned","Keep",IF(Q58="You rate higher","Justify or lower",IF(Q58="Official rates higher","Re-check scoring / raise",IF(Q58="No official equivalent","Keep as sector add-on; justify","Add or map to existing topic")))) -> Re-check scoring / raise | T58: Same official topic as G05; excluded from index. Consider merging G05+G06.
A59: G07 | B59: =INDEX('DMA Matrix'!$C$5:$C$34,MATCH($A59,'DMA Matrix'!$A$5:$A$34,0)) -> Responsible Supply Chain | C59: =INDEX('DMA Matrix'!$D$5:$D$34,MATCH($A59,'DMA Matrix'!$A$5:$A$34,0)) -> 3.4 | D59: =INDEX('DMA Matrix'!$F$5:$F$34,MATCH($A59,'DMA Matrix'!$A$5:$A$34,0)) -> 3.4 | E59: =C59*D59 -> 11.56 | F59: =RANK(E59,$E$33:$E$62,0) -> 20 | G59: =IF(F59<=$C$11,"Very High",IF(F59<=$C$12,"High","Medium")) -> High | H59: =IF(AND(C59>=$C$13,D59>=$C$13),"Tier 1",IF(AND(C59>=$C$14,D59>=$C$14),"Tier 2","Tier 3")) -> Tier 3 | I59: 18 | J59: Responsible supply chain | K59: High | L59: Low | M59: 1:1 | N59: Y | O59: =IF(K59="n/a","",IF(G59="Very High",3,IF(G59="High",2,1))-IF(K59="Very High",3,IF(K59="High",2,1))) -> 0 | P59: =IF(OR(N59="N",O59=""),"",3-ABS(O59)) -> 3 | Q59: =IF(B59="","Missing from your universe",IF(K59="n/a","No official equivalent",IF(O59=0,"Aligned",IF(O59>0,"You rate higher","Official rates higher")))) -> Aligned | R59: =IF(OR(ABS(F59-$C$11)<=1,ABS(F59-$C$12)<=1),"Edge","") | S59: =IF(Q59="Aligned","Keep",IF(Q59="You rate higher","Justify or lower",IF(Q59="Official rates higher","Re-check scoring / raise",IF(Q59="No official equivalent","Keep as sector add-on; justify","Add or map to existing topic")))) -> Keep | T59: Official dot sits on the High/Medium boundary (certainty Low).
A60: G08 | B60: =INDEX('DMA Matrix'!$C$5:$C$34,MATCH($A60,'DMA Matrix'!$A$5:$A$34,0)) -> Transparency & Accountability | C60: =INDEX('DMA Matrix'!$D$5:$D$34,MATCH($A60,'DMA Matrix'!$A$5:$A$34,0)) -> 3.1166667 | D60: =INDEX('DMA Matrix'!$F$5:$F$34,MATCH($A60,'DMA Matrix'!$A$5:$A$34,0)) -> 2.55 | E60: =C60*D60 -> 7.9475 | F60: =RANK(E60,$E$33:$E$62,0) -> 29 | G60: =IF(F60<=$C$11,"Very High",IF(F60<=$C$12,"High","Medium")) -> Medium | H60: =IF(AND(C60>=$C$13,D60>=$C$13),"Tier 1",IF(AND(C60>=$C$14,D60>=$C$14),"Tier 2","Tier 3")) -> Tier 3 | I60: 23 | J60: Transparency and accountability | K60: High | L60: High | M60: 1:1 | N60: Y | O60: =IF(K60="n/a","",IF(G60="Very High",3,IF(G60="High",2,1))-IF(K60="Very High",3,IF(K60="High",2,1))) -> -1 | P60: =IF(OR(N60="N",O60=""),"",3-ABS(O60)) -> 2 | Q60: =IF(B60="","Missing from your universe",IF(K60="n/a","No official equivalent",IF(O60=0,"Aligned",IF(O60>0,"You rate higher","Official rates higher")))) -> Official rates higher | R60: =IF(OR(ABS(F60-$C$11)<=1,ABS(F60-$C$12)<=1),"Edge","") | S60: =IF(Q60="Aligned","Keep",IF(Q60="You rate higher","Justify or lower",IF(Q60="Official rates higher","Re-check scoring / raise",IF(Q60="No official equivalent","Keep as sector add-on; justify","Add or map to existing topic")))) -> Re-check scoring / raise | T60: Official rates its financial importance higher than you do.
A61: G09 | B61: =INDEX('DMA Matrix'!$C$5:$C$34,MATCH($A61,'DMA Matrix'!$A$5:$A$34,0)) -> Innovation — Clean Technology | C61: =INDEX('DMA Matrix'!$D$5:$D$34,MATCH($A61,'DMA Matrix'!$A$5:$A$34,0)) -> 3.8 | D61: =INDEX('DMA Matrix'!$F$5:$F$34,MATCH($A61,'DMA Matrix'!$A$5:$A$34,0)) -> 4.75 | E61: =C61*D61 -> 18.05 | F61: =RANK(E61,$E$33:$E$62,0) -> 9 | G61: =IF(F61<=$C$11,"Very High",IF(F61<=$C$12,"High","Medium")) -> Very High | H61: =IF(AND(C61>=$C$13,D61>=$C$13),"Tier 1",IF(AND(C61>=$C$14,D61>=$C$14),"Tier 2","Tier 3")) -> Tier 2 | I61: 27 | J61: Innovation and collaborations | K61: High | L61: High | M61: Reframed | N61: Y | O61: =IF(K61="n/a","",IF(G61="Very High",3,IF(G61="High",2,1))-IF(K61="Very High",3,IF(K61="High",2,1))) -> 1 | P61: =IF(OR(N61="N",O61=""),"",3-ABS(O61)) -> 2 | Q61: =IF(B61="","Missing from your universe",IF(K61="n/a","No official equivalent",IF(O61=0,"Aligned",IF(O61>0,"You rate higher","Official rates higher")))) -> You rate higher | R61: =IF(OR(ABS(F61-$C$11)<=1,ABS(F61-$C$12)<=1),"Edge","") | S61: =IF(Q61="Aligned","Keep",IF(Q61="You rate higher","Justify or lower",IF(Q61="Official rates higher","Re-check scoring / raise",IF(Q61="No official equivalent","Keep as sector add-on; justify","Add or map to existing topic")))) -> Justify or lower | T61: Official also has #26 New business opportunities (last row); you rank the merged idea top band.
A62: G10 | B62: =INDEX('DMA Matrix'!$C$5:$C$34,MATCH($A62,'DMA Matrix'!$A$5:$A$34,0)) -> Creating Economic Value | C62: =INDEX('DMA Matrix'!$D$5:$D$34,MATCH($A62,'DMA Matrix'!$A$5:$A$34,0)) -> 3.1166667 | D62: =INDEX('DMA Matrix'!$F$5:$F$34,MATCH($A62,'DMA Matrix'!$A$5:$A$34,0)) -> 3.4 | E62: =C62*D62 -> 10.596667 | F62: =RANK(E62,$E$33:$E$62,0) -> 23 | G62: =IF(F62<=$C$11,"Very High",IF(F62<=$C$12,"High","Medium")) -> High | H62: =IF(AND(C62>=$C$13,D62>=$C$13),"Tier 1",IF(AND(C62>=$C$14,D62>=$C$14),"Tier 2","Tier 3")) -> Tier 3 | I62: 19 | J62: Creating economic value | K62: Very High | L62: High | M62: Reframed | N62: Y | O62: =IF(K62="n/a","",IF(G62="Very High",3,IF(G62="High",2,1))-IF(K62="Very High",3,IF(K62="High",2,1))) -> -1 | P62: =IF(OR(N62="N",O62=""),"",3-ABS(O62)) -> 2 | Q62: =IF(B62="","Missing from your universe",IF(K62="n/a","No official equivalent",IF(O62=0,"Aligned",IF(O62>0,"You rate higher","Official rates higher")))) -> Official rates higher | R62: =IF(OR(ABS(F62-$C$11)<=1,ABS(F62-$C$12)<=1),"Edge","") | S62: =IF(Q62="Aligned","Keep",IF(Q62="You rate higher","Justify or lower",IF(Q62="Official rates higher","Re-check scoring / raise",IF(Q62="No official equivalent","Keep as sector add-on; justify","Add or map to existing topic")))) -> Re-check scoring / raise | T62: ="Relabelled to the official 'Creating economic value'. Official is Very High; you score "&TEXT(C62,"0.00")&" impact / "&TEXT(D62,"0.00")&" financial." -> Relabelled to the official 'Creating economic value'. Official is Very High; you score 3.12 impact / 3.40 financial.

Sheet DMA Quality Scorecard
A1: Tata Power - DMA Quality Scorecard | FY2025–26
A2: Score 0 = not disclosed, 1 = partly disclosed, 2 = clearly disclosed. Reference points: ESRS 2 (IRO-1) and GRI 3 (3-1, 3-2). Scores are analyst judgements against the evidence shown; change them if you disagree.
C4: Grade A needs score >= | D4: 0.8
C5: Grade B needs score >= | D5: 0.65
C6: Grade C needs score >= | D6: 0.5
A8: Sr. No | B8: Criterion | C8: Good-practice reference | D8: Official DMA score (0-2) | E8: Evidence for the official score | F8: Project DMA score (0-2) | G8: Gap
A9: 1 | B9: Frameworks named | C9: ESRS 1/2, GRI 3-1 | D9: 2 | E9: ESRS, GRI, SASB, DJSI, MSCI, Sustainalytics named (AR p.78). | F9: 1 | G9: =F9-D9 -> -1
A10: 2 | B10: Both dimensions assessed and defined | C10: ESRS 1 s.3.2; GRI 3-2 | D10: 2 | E10: Impact ('inside-out') and financial ('outside-in') defined and both plotted (AR p.78-80). | F10: 2 | G10: =F10-D10 -> 0
A11: 3 | B11: Process steps disclosed | C11: GRI 3-1; ESRS 2 IRO-1 | D11: 2 | E11: Seven-step process from topic identification to leadership concurrence (AR pp.78-79). | F11: 1 | G11: =F11-D11 -> -1
A12: 4 | B12: Stakeholder engagement (who, how many, how) | C12: GRI 3-1; ESRS 1 s.3.3 | D12: 1 | E12: Groups named (employees, investors, supply chain, NGOs, media, customers) but no numbers, sample or method (AR p.79). | F12: 0 | G12: =F12-D12 -> -1
A13: 5 | B13: Scales and thresholds disclosed | C13: ESRS 1 s.3.4-3.5 | D13: 0 | E13: 'Structured scoring methodology' only; no scales or thresholds (AR p.79). | F13: 2 | G13: =F13-D13 -> 2
A14: 6 | B14: Topic-level results disclosed | C14: GRI 3-2 | D14: 1 | E14: Matrix positions plotted; no numeric scores (AR p.80). | F14: 2 | G14: =F14-D14 -> 1
A15: 7 | B15: IROs disclosed per material topic | C15: ESRS 2 IRO-1; GRI 3-3 | D15: 1 | E15: IROs given for the 10 Very High topics only (AR p.81; BRSR Q26 pp.293-295). | F15: 2 | G15: =F15-D15 -> 1
A16: 8 | B16: Time horizon and value-chain position | C16: ESRS 1 s.3.3, s.6 | D16: 1 | E16: Timeframe and upstream/own/downstream given for the 10 Very High topics (AR p.81). | F16: 1 | G16: =F16-D16 -> 0
A17: 9 | B17: Independent assurance of the DMA | C17: ESRS 1 s.3.6; GRI 3 | D17: 1 | E17: TUV reviewed the stakeholder and materiality process to validate qualitative statements (TUV India assurance statement in the Annual Report); not a full DMA assurance. | F17: 0 | G17: =F17-D17 -> -1
A18: 10 | B18: Refresh cycle and leadership approval | C18: ESRS 1 s.3.6 | D18: 2 | E18: Redone every three years; CSO review and apex leadership validation (AR pp.78-79). | F18: 0 | G18: =F18-D18 -> -2
A19: 11 | B19: Change log versus prior assessment | C19: GRI 3-2 (changes) | D19: 2 | E19: Two topics added and two renamed, with reasons (AR p.79). | F19: 0 | G19: =F19-D19 -> -2
A20: 12 | B20: Link from topics to targets and KPIs | C20: GRI 3-3; ESRS 2 | D20: 1 | E20: Targets tracked for selected topics (AR pp.72-73); not mapped topic by topic. | F20: 2 | G20: =F20-D20 -> 1
B21: Total (max 24) | D21: =SUM(D9:D20) -> 16 | F21: =SUM(F9:F20) -> 13 | G21: =F21-D21 -> -3
B22: Score % | D22: =D21/(2*COUNT(D9:D20)) -> 0.66666667 | F22: =F21/(2*COUNT(F9:F20)) -> 0.54166667
B23: Grade | D23: =IF(D22>=$D$4,"A",IF(D22>=$D$5,"B",IF(D22>=$D$6,"C","D"))) -> B | F23: =IF(F22>=$D$4,"A",IF(F22>=$D$5,"B",IF(F22>=$D$6,"C","D"))) -> C
B24: Reading | E24: Official: strong on process, governance and change log; thin on scales, thresholds and topic-level numbers.
